{
"meta":{"test_sets":[],"test_metrics":[],"learn_metrics":[{"best_value":"Min","name":"RMSE"}],"launch_mode":"Train","parameters":"","iteration_count":1000,"learn_sets":["learn"],"name":"experiment"},
"iterations":[
{"learn":[3974.11511],"iteration":0,"passed_time":0.0008958103044,"remaining_time":0.8949144941},
{"learn":[3917.40741],"iteration":1,"passed_time":0.001656709418,"remaining_time":0.8266979998},
{"learn":[3861.731423],"iteration":2,"passed_time":0.002362672896,"remaining_time":0.7851949591},
{"learn":[3801.526757],"iteration":3,"passed_time":0.003174744817,"remaining_time":0.7905114595},
{"learn":[3747.563413],"iteration":4,"passed_time":0.003942402006,"remaining_time":0.7845379991},
{"learn":[3694.363637],"iteration":5,"passed_time":0.004691306789,"remaining_time":0.7771931581},
{"learn":[3636.924948],"iteration":6,"passed_time":0.00543132095,"remaining_time":0.7704716719},
{"learn":[3586.273751],"iteration":7,"passed_time":0.006157388447,"remaining_time":0.7635161675},
{"learn":[3538.362207],"iteration":8,"passed_time":0.006910478231,"remaining_time":0.7609204363},
{"learn":[3490.039134],"iteration":9,"passed_time":0.007442824272,"remaining_time":0.736839603},
{"learn":[3439.135333],"iteration":10,"passed_time":0.008226149347,"remaining_time":0.7396056095},
{"learn":[3392.499291],"iteration":11,"passed_time":0.00894351645,"remaining_time":0.736349521},
{"learn":[3345.14599],"iteration":12,"passed_time":0.009717911689,"remaining_time":0.7378137567},
{"learn":[3300.347589],"iteration":13,"passed_time":0.01046889896,"remaining_time":0.7373095982},
{"learn":[3255.757839],"iteration":14,"passed_time":0.01121680255,"remaining_time":0.7365700339},
{"learn":[3212.301686],"iteration":15,"passed_time":0.01197365683,"remaining_time":0.7363798949},
{"learn":[3169.955479],"iteration":16,"passed_time":0.01269806234,"remaining_time":0.7342467812},
{"learn":[3126.574705],"iteration":17,"passed_time":0.01354223261,"remaining_time":0.7388040236},
{"learn":[3081.180966],"iteration":18,"passed_time":0.0142743173,"remaining_time":0.7370055406},
{"learn":[3041.253198],"iteration":19,"passed_time":0.01499121384,"remaining_time":0.7345694781},
{"learn":[2998.771271],"iteration":20,"passed_time":0.01591845169,"remaining_time":0.7421030575},
{"learn":[2960.013256],"iteration":21,"passed_time":0.01665469134,"remaining_time":0.7403767334},
{"learn":[2914.136919],"iteration":22,"passed_time":0.01740559852,"remaining_time":0.7393595545},
{"learn":[2873.085522],"iteration":23,"passed_time":0.01812621951,"remaining_time":0.7371329267},
{"learn":[2836.518212],"iteration":24,"passed_time":0.01887559486,"remaining_time":0.7361481994},
{"learn":[2800.448581],"iteration":25,"passed_time":0.01961666027,"remaining_time":0.7348702733},
{"learn":[2764.983466],"iteration":26,"passed_time":0.02037197271,"remaining_time":0.7341455351},
{"learn":[2730.388853],"iteration":27,"passed_time":0.0210979501,"remaining_time":0.7324002678},
{"learn":[2696.591819],"iteration":28,"passed_time":0.02181384545,"remaining_time":0.7303877216},
{"learn":[2659.408935],"iteration":29,"passed_time":0.02253831103,"remaining_time":0.7287387233},
{"learn":[2626.919386],"iteration":30,"passed_time":0.02327968598,"remaining_time":0.7276779264},
{"learn":[2593.233988],"iteration":31,"passed_time":0.02402768969,"remaining_time":0.7268376131},
{"learn":[2561.796479],"iteration":32,"passed_time":0.02477783596,"remaining_time":0.7260656779},
{"learn":[2529.513176],"iteration":33,"passed_time":0.02552827257,"remaining_time":0.7253032736},
{"learn":[2499.03128],"iteration":34,"passed_time":0.02628829063,"remaining_time":0.7248057274},
{"learn":[2469.565508],"iteration":35,"passed_time":0.02703078776,"remaining_time":0.7238244277},
{"learn":[2439.569992],"iteration":36,"passed_time":0.02801738654,"remaining_time":0.7292092766},
{"learn":[2411.016489],"iteration":37,"passed_time":0.02896149455,"remaining_time":0.7331830988},
{"learn":[2379.598951],"iteration":38,"passed_time":0.02972113215,"remaining_time":0.7323591794},
{"learn":[2352.318716],"iteration":39,"passed_time":0.03050768191,"remaining_time":0.7321843659},
{"learn":[2321.910676],"iteration":40,"passed_time":0.03123467051,"remaining_time":0.7305865615},
{"learn":[2295.682811],"iteration":41,"passed_time":0.03198936221,"remaining_time":0.729662119},
{"learn":[2269.277265],"iteration":42,"passed_time":0.03269762844,"remaining_time":0.7277123352},
{"learn":[2241.265707],"iteration":43,"passed_time":0.03341808924,"remaining_time":0.7260839389},
{"learn":[2216.308241],"iteration":44,"passed_time":0.03418118097,"remaining_time":0.7254006184},
{"learn":[2190.36535],"iteration":45,"passed_time":0.03491865209,"remaining_time":0.7241824804},
{"learn":[2162.990512],"iteration":46,"passed_time":0.03564703235,"remaining_time":0.7228004645},
{"learn":[2139.59214],"iteration":47,"passed_time":0.03646966439,"remaining_time":0.7233150104},
{"learn":[2112.611016],"iteration":48,"passed_time":0.03720656483,"remaining_time":0.7221110848},
{"learn":[2089.554054],"iteration":49,"passed_time":0.03794555777,"remaining_time":0.7209655977},
{"learn":[2063.254899],"iteration":50,"passed_time":0.03869000723,"remaining_time":0.7199375856},
{"learn":[2040.423145],"iteration":51,"passed_time":0.03941282084,"remaining_time":0.7185260415},
{"learn":[2015.259121],"iteration":52,"passed_time":0.04014860996,"remaining_time":0.7173723326},
{"learn":[1993.768527],"iteration":53,"passed_time":0.04087517805,"remaining_time":0.7160725636},
{"learn":[1973.490558],"iteration":54,"passed_time":0.04139745206,"remaining_time":0.7112834945},
{"learn":[1946.40126],"iteration":55,"passed_time":0.042234513,"remaining_time":0.7119532192},
{"learn":[1926.716415],"iteration":56,"passed_time":0.04297465732,"remaining_time":0.7109666992},
{"learn":[1904.199099],"iteration":57,"passed_time":0.0437133499,"remaining_time":0.7099650967},
{"learn":[1882.184279],"iteration":58,"passed_time":0.04445300363,"remaining_time":0.7089877359},
{"learn":[1863.867393],"iteration":59,"passed_time":0.04498757233,"remaining_time":0.7048052998},
{"learn":[1842.575048],"iteration":60,"passed_time":0.04576056589,"remaining_time":0.7044126455},
{"learn":[1821.880416],"iteration":61,"passed_time":0.04650544587,"remaining_time":0.7035823907},
{"learn":[1801.458199],"iteration":62,"passed_time":0.04725394016,"remaining_time":0.7028086021},
{"learn":[1782.032917],"iteration":63,"passed_time":0.04799697793,"remaining_time":0.7019558023},
{"learn":[1764.11757],"iteration":64,"passed_time":0.04874070653,"remaining_time":0.7011163171},
{"learn":[1745.53433],"iteration":65,"passed_time":0.04949654961,"remaining_time":0.7004511717},
{"learn":[1729.551423],"iteration":66,"passed_time":0.05012263765,"remaining_time":0.6979764317},
{"learn":[1713.813509],"iteration":67,"passed_time":0.0508747763,"remaining_time":0.6972836987},
{"learn":[1698.39423],"iteration":68,"passed_time":0.05163409352,"remaining_time":0.6966861024},
{"learn":[1680.817839],"iteration":69,"passed_time":0.05238512084,"remaining_time":0.6959737483},
{"learn":[1663.693923],"iteration":70,"passed_time":0.05315862501,"remaining_time":0.6955544034},
{"learn":[1651.150255],"iteration":71,"passed_time":0.05390951217,"remaining_time":0.6948337124},
{"learn":[1638.728881],"iteration":72,"passed_time":0.05466605608,"remaining_time":0.6941840272},
{"learn":[1625.912551],"iteration":73,"passed_time":0.05540149477,"remaining_time":0.6932673535},
{"learn":[1609.246629],"iteration":74,"passed_time":0.05644928666,"remaining_time":0.6962078688},
{"learn":[1592.819573],"iteration":75,"passed_time":0.05729338518,"remaining_time":0.6965669461},
{"learn":[1576.163928],"iteration":76,"passed_time":0.05804703563,"remaining_time":0.69581057},
{"learn":[1562.289787],"iteration":77,"passed_time":0.0587929168,"remaining_time":0.6949624268},
{"learn":[1548.876812],"iteration":78,"passed_time":0.05952672355,"remaining_time":0.6939761062},
{"learn":[1539.206611],"iteration":79,"passed_time":0.06030356171,"remaining_time":0.6934909596},
{"learn":[1521.36297],"iteration":80,"passed_time":0.06104717016,"remaining_time":0.6926215973},
{"learn":[1512.262918],"iteration":81,"passed_time":0.06181374606,"remaining_time":0.6920124254},
{"learn":[1498.700349],"iteration":82,"passed_time":0.06254644148,"remaining_time":0.6910251426},
{"learn":[1485.532601],"iteration":83,"passed_time":0.06328288137,"remaining_time":0.6900847539},
{"learn":[1474.240314],"iteration":84,"passed_time":0.06403391953,"remaining_time":0.6893063102},
{"learn":[1461.499192],"iteration":85,"passed_time":0.06477020924,"remaining_time":0.6883717587},
{"learn":[1449.698818],"iteration":86,"passed_time":0.06550935236,"remaining_time":0.6874717093},
{"learn":[1436.568398],"iteration":87,"passed_time":0.06626107885,"remaining_time":0.6867057263},
{"learn":[1427.281879],"iteration":88,"passed_time":0.06700826241,"remaining_time":0.6858935624},
{"learn":[1418.501036],"iteration":89,"passed_time":0.06778086551,"remaining_time":0.6853398624},
{"learn":[1407.371767],"iteration":90,"passed_time":0.06853761967,"remaining_time":0.684623036},
{"learn":[1396.811784],"iteration":91,"passed_time":0.0692749306,"remaining_time":0.6837134455},
{"learn":[1389.189668],"iteration":92,"passed_time":0.0700373215,"remaining_time":0.683052157},
{"learn":[1377.63442],"iteration":93,"passed_time":0.07083157963,"remaining_time":0.6826958633},
{"learn":[1366.377822],"iteration":94,"passed_time":0.07160109905,"remaining_time":0.6820946804},
{"learn":[1357.922301],"iteration":95,"passed_time":0.07236256884,"remaining_time":0.68141419},
{"learn":[1349.917585],"iteration":96,"passed_time":0.0731073487,"remaining_time":0.6805766585},
{"learn":[1339.171365],"iteration":97,"passed_time":0.0738411154,"remaining_time":0.6796396539},
{"learn":[1332.045764],"iteration":98,"passed_time":0.07455819215,"remaining_time":0.6785548599},
{"learn":[1320.092086],"iteration":99,"passed_time":0.07529167851,"remaining_time":0.6776251066},
{"learn":[1310.157303],"iteration":100,"passed_time":0.0760475316,"remaining_time":0.6768983258},
{"learn":[1299.356919],"iteration":101,"passed_time":0.07678936794,"remaining_time":0.6760475726},
{"learn":[1288.58765],"iteration":102,"passed_time":0.07752675896,"remaining_time":0.6751602213},
{"learn":[1281.541733],"iteration":103,"passed_time":0.07824916208,"remaining_time":0.6741466272},
{"learn":[1271.803001],"iteration":104,"passed_time":0.07902679118,"remaining_time":0.6736093153},
{"learn":[1263.281717],"iteration":105,"passed_time":0.07976301081,"remaining_time":0.6727182233},
{"learn":[1255.194221],"iteration":106,"passed_time":0.08049163136,"remaining_time":0.6717666056},
{"learn":[1249.273352],"iteration":107,"passed_time":0.08122807125,"remaining_time":0.6708836996},
{"learn":[1242.673399],"iteration":108,"passed_time":0.08203729811,"remaining_time":0.6705984643},
{"learn":[1236.7803],"iteration":109,"passed_time":0.08299681453,"remaining_time":0.6715196812},
{"learn":[1226.906833],"iteration":110,"passed_time":0.08385683207,"remaining_time":0.6716101235},
{"learn":[1221.167034],"iteration":111,"passed_time":0.08458420112,"remaining_time":0.6706318803},
{"learn":[1214.386234],"iteration":112,"passed_time":0.08533302581,"remaining_time":0.6698264946},
{"learn":[1205.069854],"iteration":113,"passed_time":0.08637538203,"remaining_time":0.6713034077},
{"learn":[1197.792265],"iteration":114,"passed_time":0.08732807113,"remaining_time":0.6720464604},
{"learn":[1191.111313],"iteration":115,"passed_time":0.08808422457,"remaining_time":0.671262539},
{"learn":[1185.278501],"iteration":116,"passed_time":0.08888134613,"remaining_time":0.6707882789},
{"learn":[1178.63087],"iteration":117,"passed_time":0.08965426044,"remaining_time":0.6701276077},
{"learn":[1173.408658],"iteration":118,"passed_time":0.09040979314,"remaining_time":0.6693363677},
{"learn":[1167.121929],"iteration":119,"passed_time":0.09119405016,"remaining_time":0.6687563678},
{"learn":[1161.769992],"iteration":120,"passed_time":0.0919573121,"remaining_time":0.6680204738},
{"learn":[1154.316105],"iteration":121,"passed_time":0.09279061689,"remaining_time":0.6677882101},
{"learn":[1149.328678],"iteration":122,"passed_time":0.0937202184,"remaining_time":0.6682327767},
{"learn":[1142.231099],"iteration":123,"passed_time":0.09459283015,"remaining_time":0.6682525743},
{"learn":[1136.112093],"iteration":124,"passed_time":0.09545998622,"remaining_time":0.6682199035},
{"learn":[1129.018609],"iteration":125,"passed_time":0.09619695675,"remaining_time":0.6672709539},
{"learn":[1123.747584],"iteration":126,"passed_time":0.09693032296,"remaining_time":0.6663005665},
{"learn":[1114.80647],"iteration":127,"passed_time":0.09766290825,"remaining_time":0.6653285624},
{"learn":[1107.206166],"iteration":128,"passed_time":0.09842822264,"remaining_time":0.6645812552},
{"learn":[1100.598375],"iteration":129,"passed_time":0.0991756056,"remaining_time":0.6637136683},
{"learn":[1094.079349],"iteration":130,"passed_time":0.1000448041,"remaining_time":0.6636559906},
{"learn":[1089.446771],"iteration":131,"passed_time":0.100960086,"remaining_time":0.6638890505},
{"learn":[1081.33584],"iteration":132,"passed_time":0.1017308077,"remaining_time":0.6631624833},
{"learn":[1073.445379],"iteration":133,"passed_time":0.102563012,"remaining_time":0.6628326},
{"learn":[1069.380626],"iteration":134,"passed_time":0.103317934,"remaining_time":0.6620000955},
{"learn":[1065.467251],"iteration":135,"passed_time":0.1041613417,"remaining_time":0.6617308765},
{"learn":[1057.762025],"iteration":136,"passed_time":0.1049601761,"remaining_time":0.6611724962},
{"learn":[1053.070199],"iteration":137,"passed_time":0.1057197336,"remaining_time":0.6603652926},
{"learn":[1048.788526],"iteration":138,"passed_time":0.1066181671,"remaining_time":0.660419006},
{"learn":[1044.739762],"iteration":139,"passed_time":0.1074545664,"remaining_time":0.6600780506},
{"learn":[1038.791841],"iteration":140,"passed_time":0.1081977443,"remaining_time":0.6591621445},
{"learn":[1037.247314],"iteration":141,"passed_time":0.1086473215,"remaining_time":0.6564746607},
{"learn":[1033.173911],"iteration":142,"passed_time":0.1093781046,"remaining_time":0.6555037458},
{"learn":[1028.881657],"iteration":143,"passed_time":0.1100924881,"remaining_time":0.6544386795},
{"learn":[1023.962248],"iteration":144,"passed_time":0.1108420737,"remaining_time":0.653586021},
{"learn":[1020.464461],"iteration":145,"passed_time":0.1117219756,"remaining_time":0.6534970353},
{"learn":[1016.682593],"iteration":146,"passed_time":0.1125540901,"remaining_time":0.653119992},
{"learn":[1012.821726],"iteration":147,"passed_time":0.113318984,"remaining_time":0.6523498266},
{"learn":[1007.61393],"iteration":148,"passed_time":0.1140776704,"remaining_time":0.6515442788},
{"learn":[1003.857889],"iteration":149,"passed_time":0.1150682737,"remaining_time":0.652053551},
{"learn":[1000.373098],"iteration":150,"passed_time":0.1159903654,"remaining_time":0.6521577499},
{"learn":[995.7775365],"iteration":151,"passed_time":0.1168562294,"remaining_time":0.6519347534},
{"learn":[993.8291517],"iteration":152,"passed_time":0.1176380635,"remaining_time":0.6512381686},
{"learn":[989.6124159],"iteration":153,"passed_time":0.118395929,"remaining_time":0.6504088048},
{"learn":[986.5012476],"iteration":154,"passed_time":0.1193411483,"remaining_time":0.6506017442},
{"learn":[984.6706303],"iteration":155,"passed_time":0.1202618183,"remaining_time":0.6506472736},
{"learn":[978.2337435],"iteration":156,"passed_time":0.121034031,"remaining_time":0.6498833638},
{"learn":[971.7811101],"iteration":157,"passed_time":0.121778961,"remaining_time":0.6489739568},
{"learn":[964.6220633],"iteration":158,"passed_time":0.1225894786,"remaining_time":0.6484135313},
{"learn":[961.8121985],"iteration":159,"passed_time":0.1231508893,"remaining_time":0.6465421691},
{"learn":[956.2422478],"iteration":160,"passed_time":0.1239518964,"remaining_time":0.6459356588},
{"learn":[950.740894],"iteration":161,"passed_time":0.1246908493,"remaining_time":0.6450057512},
{"learn":[948.9053871],"iteration":162,"passed_time":0.1254808832,"remaining_time":0.6443404861},
{"learn":[945.2086883],"iteration":163,"passed_time":0.1264175515,"remaining_time":0.6444211771},
{"learn":[943.3919039],"iteration":164,"passed_time":0.1273662358,"remaining_time":0.6445503448},
{"learn":[941.5956999],"iteration":165,"passed_time":0.1281061999,"remaining_time":0.6436178959},
{"learn":[937.6476311],"iteration":166,"passed_time":0.1290253589,"remaining_time":0.6435815808},
{"learn":[933.7963745],"iteration":167,"passed_time":0.1298729107,"remaining_time":0.6431801294},
{"learn":[929.200407],"iteration":168,"passed_time":0.1306599119,"remaining_time":0.6424756614},
{"learn":[922.9374176],"iteration":169,"passed_time":0.1315911136,"remaining_time":0.6424742607},
{"learn":[916.7680606],"iteration":170,"passed_time":0.1326344802,"remaining_time":0.6430057551},
{"learn":[913.9502814],"iteration":171,"passed_time":0.1333803013,"remaining_time":0.6420865669},
{"learn":[908.5596055],"iteration":172,"passed_time":0.1341707157,"remaining_time":0.6413825543},
{"learn":[905.7407201],"iteration":173,"passed_time":0.1349441899,"remaining_time":0.6405971311},
{"learn":[903.9483805],"iteration":174,"passed_time":0.1356735413,"remaining_time":0.6396038374},
{"learn":[902.3090419],"iteration":175,"passed_time":0.1365172593,"remaining_time":0.6391489869},
{"learn":[900.6245783],"iteration":176,"passed_time":0.1373431453,"remaining_time":0.638606828},
{"learn":[896.3948607],"iteration":177,"passed_time":0.1384886739,"remaining_time":0.6395375841},
{"learn":[892.0598129],"iteration":178,"passed_time":0.1395673227,"remaining_time":0.6401383906},
{"learn":[888.5322744],"iteration":179,"passed_time":0.1407629304,"remaining_time":0.6412533494},
{"learn":[883.7065277],"iteration":180,"passed_time":0.1419034639,"remaining_time":0.6420935741},
{"learn":[877.0728761],"iteration":181,"passed_time":0.1430458493,"remaining_time":0.6429203559},
{"learn":[875.1972963],"iteration":182,"passed_time":0.1440608515,"remaining_time":0.6431569163},
{"learn":[873.6565739],"iteration":183,"passed_time":0.1449501148,"remaining_time":0.6428222483},
{"learn":[869.769684],"iteration":184,"passed_time":0.1458725161,"remaining_time":0.6426275708},
{"learn":[864.9772281],"iteration":185,"passed_time":0.1466746244,"remaining_time":0.6418986251},
{"learn":[860.0615061],"iteration":186,"passed_time":0.1475024635,"remaining_time":0.6412807638},
{"learn":[856.4147151],"iteration":187,"passed_time":0.148301368,"remaining_time":0.640535696},
{"learn":[852.6062167],"iteration":188,"passed_time":0.1491407309,"remaining_time":0.6399636654},
{"learn":[848.922385],"iteration":189,"passed_time":0.1498981458,"remaining_time":0.6390394639},
{"learn":[846.3189754],"iteration":190,"passed_time":0.1506615179,"remaining_time":0.6381422408},
{"learn":[841.1083144],"iteration":191,"passed_time":0.1515315978,"remaining_time":0.6376954739},
{"learn":[836.7567447],"iteration":192,"passed_time":0.1523743244,"remaining_time":0.6371299469},
{"learn":[832.4562957],"iteration":193,"passed_time":0.153348879,"remaining_time":0.6371092603},
{"learn":[830.7147427],"iteration":194,"passed_time":0.154216806,"remaining_time":0.6366386094},
{"learn":[827.1971919],"iteration":195,"passed_time":0.1550891875,"remaining_time":0.6361821772},
{"learn":[823.0831252],"iteration":196,"passed_time":0.1559663864,"remaining_time":0.6357411587},
{"learn":[819.5238609],"iteration":197,"passed_time":0.157021457,"remaining_time":0.6360162045},
{"learn":[815.4594868],"iteration":198,"passed_time":0.1581257956,"remaining_time":0.6364761923},
{"learn":[811.137902],"iteration":199,"passed_time":0.1591202137,"remaining_time":0.6364808549},
{"learn":[807.7774238],"iteration":200,"passed_time":0.160001797,"remaining_time":0.6360270439},
{"learn":[803.6985169],"iteration":201,"passed_time":0.1608660396,"remaining_time":0.6355004931},
{"learn":[800.4152884],"iteration":202,"passed_time":0.1616010678,"remaining_time":0.6344633056},
{"learn":[797.3879316],"iteration":203,"passed_time":0.162457792,"remaining_time":0.6339039334},
{"learn":[794.2260609],"iteration":204,"passed_time":0.1633326075,"remaining_time":0.6334118192},
{"learn":[791.6460842],"iteration":205,"passed_time":0.1643021359,"remaining_time":0.6332810479},
{"learn":[787.9260264],"iteration":206,"passed_time":0.1653141041,"remaining_time":0.6333047563},
{"learn":[785.7940195],"iteration":207,"passed_time":0.1661026062,"remaining_time":0.6324676159},
{"learn":[782.2090415],"iteration":208,"passed_time":0.1670737254,"remaining_time":0.6323220898},
{"learn":[780.3188573],"iteration":209,"passed_time":0.1679142196,"remaining_time":0.6316773022},
{"learn":[778.8668066],"iteration":210,"passed_time":0.1686546843,"remaining_time":0.6306566156},
{"learn":[775.8330985],"iteration":211,"passed_time":0.1694082146,"remaining_time":0.6296871373},
{"learn":[771.4172964],"iteration":212,"passed_time":0.1704283835,"remaining_time":0.6297048723},
{"learn":[769.6359981],"iteration":213,"passed_time":0.1715917829,"remaining_time":0.6302389785},
{"learn":[767.8429164],"iteration":214,"passed_time":0.1725191009,"remaining_time":0.6298953219},
{"learn":[763.5616202],"iteration":215,"passed_time":0.1734138399,"remaining_time":0.6294280115},
{"learn":[760.7110932],"iteration":216,"passed_time":0.1741676305,"remaining_time":0.6284481784},
{"learn":[756.2638708],"iteration":217,"passed_time":0.1749921757,"remaining_time":0.6277242266},
{"learn":[753.5161746],"iteration":218,"passed_time":0.1757913706,"remaining_time":0.6269089516},
{"learn":[749.1818406],"iteration":219,"passed_time":0.1767093173,"remaining_time":0.6265148523},
{"learn":[744.8980543],"iteration":220,"passed_time":0.1776170127,"remaining_time":0.6260798772},
{"learn":[741.4270888],"iteration":221,"passed_time":0.1785562841,"remaining_time":0.6257513018},
{"learn":[739.7281189],"iteration":222,"passed_time":0.1793025357,"remaining_time":0.6247447095},
{"learn":[735.918057],"iteration":223,"passed_time":0.1802892246,"remaining_time":0.6245733851},
{"learn":[732.9693302],"iteration":224,"passed_time":0.1813141391,"remaining_time":0.6245264791},
{"learn":[730.761456],"iteration":225,"passed_time":0.1823441706,"remaining_time":0.6244884427},
{"learn":[726.8479457],"iteration":226,"passed_time":0.183296989,"remaining_time":0.6241787336},
{"learn":[725.0604744],"iteration":227,"passed_time":0.1842530822,"remaining_time":0.6238744713},
{"learn":[722.7561314],"iteration":228,"passed_time":0.1851940464,"remaining_time":0.62351358},
{"learn":[721.1608949],"iteration":229,"passed_time":0.1859158789,"remaining_time":0.6224140293},
{"learn":[717.95927],"iteration":230,"passed_time":0.1867977133,"remaining_time":0.6218503963},
{"learn":[715.4229745],"iteration":231,"passed_time":0.1876288655,"remaining_time":0.6211162445},
{"learn":[713.8922723],"iteration":232,"passed_time":0.188471131,"remaining_time":0.6204178434},
{"learn":[712.6164878],"iteration":233,"passed_time":0.1893875268,"remaining_time":0.6199608782},
{"learn":[709.7751497],"iteration":234,"passed_time":0.1903798916,"remaining_time":0.6197473067},
{"learn":[708.31673],"iteration":235,"passed_time":0.1912352636,"remaining_time":0.6190836499},
{"learn":[706.8894464],"iteration":236,"passed_time":0.1921092386,"remaining_time":0.6184782662},
{"learn":[703.9382573],"iteration":237,"passed_time":0.1928760849,"remaining_time":0.617527633},
{"learn":[702.7364354],"iteration":238,"passed_time":0.1936548044,"remaining_time":0.6166163438},
{"learn":[700.9928966],"iteration":239,"passed_time":0.1945337145,"remaining_time":0.6160234294},
{"learn":[699.6302103],"iteration":240,"passed_time":0.1954025943,"remaining_time":0.6153965523},
{"learn":[697.7397456],"iteration":241,"passed_time":0.1962689286,"remaining_time":0.614759702},
{"learn":[696.0883194],"iteration":242,"passed_time":0.1970890885,"remaining_time":0.6139771194},
{"learn":[692.2095418],"iteration":243,"passed_time":0.1978519199,"remaining_time":0.6130166044},
{"learn":[688.5549011],"iteration":244,"passed_time":0.1988505233,"remaining_time":0.6127842658},
{"learn":[687.2733968],"iteration":245,"passed_time":0.1997196301,"remaining_time":0.6121487848},
{"learn":[686.1787516],"iteration":246,"passed_time":0.2004947862,"remaining_time":0.611224996},
{"learn":[682.4019375],"iteration":247,"passed_time":0.2013827772,"remaining_time":0.6106445501},
{"learn":[680.7989123],"iteration":248,"passed_time":0.2021317821,"remaining_time":0.6096424431},
{"learn":[677.0098317],"iteration":249,"passed_time":0.2030397461,"remaining_time":0.6091192382},
{"learn":[673.3496948],"iteration":250,"passed_time":0.2039188965,"remaining_time":0.6085069859},
{"learn":[670.0125003],"iteration":251,"passed_time":0.2046870943,"remaining_time":0.6075632799},
{"learn":[668.1445392],"iteration":252,"passed_time":0.2055339862,"remaining_time":0.6068533109},
{"learn":[666.1436002],"iteration":253,"passed_time":0.2064627659,"remaining_time":0.606382769},
{"learn":[664.622247],"iteration":254,"passed_time":0.2072025097,"remaining_time":0.6053563519},
{"learn":[661.6516463],"iteration":255,"passed_time":0.2081515428,"remaining_time":0.6049404211},
{"learn":[660.2802306],"iteration":256,"passed_time":0.2089339175,"remaining_time":0.6040385242},
{"learn":[657.7706634],"iteration":257,"passed_time":0.2097945249,"remaining_time":0.6033625485},
{"learn":[656.3539474],"iteration":258,"passed_time":0.2107133728,"remaining_time":0.6028517731},
{"learn":[653.3271077],"iteration":259,"passed_time":0.2118241099,"remaining_time":0.602884005},
{"learn":[650.1769099],"iteration":260,"passed_time":0.2127798618,"remaining_time":0.6024686508},
{"learn":[649.0311691],"iteration":261,"passed_time":0.21354002,"remaining_time":0.6014982243},
{"learn":[646.0459485],"iteration":262,"passed_time":0.2143812259,"remaining_time":0.6007565152},
{"learn":[643.4366152],"iteration":263,"passed_time":0.2151578138,"remaining_time":0.5998339051},
{"learn":[641.7743549],"iteration":264,"passed_time":0.2161198232,"remaining_time":0.5994266794},
{"learn":[638.7027949],"iteration":265,"passed_time":0.2169713906,"remaining_time":0.598710529},
{"learn":[637.6356661],"iteration":266,"passed_time":0.217784563,"remaining_time":0.5978879576},
{"learn":[634.6403063],"iteration":267,"passed_time":0.2186855495,"remaining_time":0.5973053069},
{"learn":[631.4467419],"iteration":268,"passed_time":0.2194616668,"remaining_time":0.5963809607},
{"learn":[629.6397095],"iteration":269,"passed_time":0.2203597404,"remaining_time":0.5957874462},
{"learn":[628.4950706],"iteration":270,"passed_time":0.2212786285,"remaining_time":0.595247676},
{"learn":[626.0786453],"iteration":271,"passed_time":0.2221454039,"remaining_time":0.5945656397},
{"learn":[623.9447489],"iteration":272,"passed_time":0.2229380509,"remaining_time":0.5936848462},
{"learn":[622.2100812],"iteration":273,"passed_time":0.2237577798,"remaining_time":0.5928764529},
{"learn":[620.6960991],"iteration":274,"passed_time":0.2247411146,"remaining_time":0.5924993022},
{"learn":[618.7636738],"iteration":275,"passed_time":0.2255600937,"remaining_time":0.5916866226},
{"learn":[617.9727703],"iteration":276,"passed_time":0.2263113313,"remaining_time":0.5906970849},
{"learn":[614.6856622],"iteration":277,"passed_time":0.2272601054,"remaining_time":0.5902222881},
{"learn":[613.8342383],"iteration":278,"passed_time":0.2281182009,"remaining_time":0.5895097594},
{"learn":[610.6708529],"iteration":279,"passed_time":0.2290700173,"remaining_time":0.5890371874},
{"learn":[608.983692],"iteration":280,"passed_time":0.2300188626,"remaining_time":0.5885536023},
{"learn":[608.2207332],"iteration":281,"passed_time":0.2309563035,"remaining_time":0.5880376806},
{"learn":[607.4777682],"iteration":282,"passed_time":0.2318527054,"remaining_time":0.5874148048},
{"learn":[604.8561303],"iteration":283,"passed_time":0.2326359612,"remaining_time":0.5865047472},
{"learn":[603.2227179],"iteration":284,"passed_time":0.2336371174,"remaining_time":0.5861422418},
{"learn":[601.6197458],"iteration":285,"passed_time":0.2345169878,"remaining_time":0.58547248},
{"learn":[598.4601198],"iteration":286,"passed_time":0.2354129383,"remaining_time":0.584841202},
{"learn":[597.4206298],"iteration":287,"passed_time":0.2361554554,"remaining_time":0.5838287648},
{"learn":[596.6814723],"iteration":288,"passed_time":0.2369897923,"remaining_time":0.583044091},
{"learn":[593.8478635],"iteration":289,"passed_time":0.2378409993,"remaining_time":0.5823003776},
{"learn":[593.1377942],"iteration":290,"passed_time":0.2387841862,"remaining_time":0.5817800275},
{"learn":[591.521356],"iteration":291,"passed_time":0.2399415596,"remaining_time":0.5817761102},
{"learn":[590.0017872],"iteration":292,"passed_time":0.2408481522,"remaining_time":0.5811591932},
{"learn":[587.4786908],"iteration":293,"passed_time":0.2416695441,"remaining_time":0.580335708},
{"learn":[586.7975462],"iteration":294,"passed_time":0.2425438582,"remaining_time":0.579638712},
{"learn":[586.1342122],"iteration":295,"passed_time":0.2433545076,"remaining_time":0.5787890992},
{"learn":[584.3551548],"iteration":296,"passed_time":0.2442513291,"remaining_time":0.5781437184},
{"learn":[582.9770802],"iteration":297,"passed_time":0.2450415833,"remaining_time":0.577245609},
{"learn":[580.2884574],"iteration":298,"passed_time":0.2460073764,"remaining_time":0.5767597687},
{"learn":[577.6702166],"iteration":299,"passed_time":0.2469318701,"remaining_time":0.5761743636},
{"learn":[576.4084395],"iteration":300,"passed_time":0.2479357604,"remaining_time":0.5757710848},
{"learn":[575.7674645],"iteration":301,"passed_time":0.2487246521,"remaining_time":0.5748669112},
{"learn":[575.1432124],"iteration":302,"passed_time":0.2494656675,"remaining_time":0.5738533671},
{"learn":[573.6380882],"iteration":303,"passed_time":0.2503487426,"remaining_time":0.573166858},
{"learn":[573.0323242],"iteration":304,"passed_time":0.2511917097,"remaining_time":0.5723876664},
{"learn":[570.3504748],"iteration":305,"passed_time":0.2521894518,"remaining_time":0.5719590836},
{"learn":[569.205333],"iteration":306,"passed_time":0.2532095798,"remaining_time":0.5715773252},
{"learn":[568.317821],"iteration":307,"passed_time":0.2540726115,"remaining_time":0.5708384649},
{"learn":[566.9317454],"iteration":308,"passed_time":0.2548977577,"remaining_time":0.5700140795},
{"learn":[565.6838731],"iteration":309,"passed_time":0.2558310419,"remaining_time":0.5694303836},
{"learn":[563.7411098],"iteration":310,"passed_time":0.2567254506,"remaining_time":0.5687583133},
{"learn":[562.4147862],"iteration":311,"passed_time":0.2576035806,"remaining_time":0.5680489213},
{"learn":[561.1125335],"iteration":312,"passed_time":0.2585115051,"remaining_time":0.5674038466},
{"learn":[559.8044676],"iteration":313,"passed_time":0.2595467514,"remaining_time":0.5670352595},
{"learn":[559.2159921],"iteration":314,"passed_time":0.2604584816,"remaining_time":0.5663938409},
{"learn":[557.359623],"iteration":315,"passed_time":0.2613809237,"remaining_time":0.5657738981},
{"learn":[556.7845589],"iteration":316,"passed_time":0.2622576203,"remaining_time":0.5650534848},
{"learn":[556.2245541],"iteration":317,"passed_time":0.2630819561,"remaining_time":0.5642197926},
{"learn":[554.9809495],"iteration":318,"passed_time":0.263983983,"remaining_time":0.5635520138},
{"learn":[553.75954],"iteration":319,"passed_time":0.2648607305,"remaining_time":0.5628290523},
{"learn":[553.2449974],"iteration":320,"passed_time":0.2658210287,"remaining_time":0.5622818644},
{"learn":[552.6574421],"iteration":321,"passed_time":0.2667943908,"remaining_time":0.5617596179},
{"learn":[551.4364537],"iteration":322,"passed_time":0.2678936239,"remaining_time":0.5614984005},
{"learn":[549.0958124],"iteration":323,"passed_time":0.2687535213,"remaining_time":0.5607326555},
{"learn":[547.7772657],"iteration":324,"passed_time":0.2696629979,"remaining_time":0.5600693034},
{"learn":[546.5954778],"iteration":325,"passed_time":0.2705814052,"remaining_time":0.5594229053},
{"learn":[546.0660727],"iteration":326,"passed_time":0.2714358767,"remaining_time":0.5586432569},
{"learn":[543.7345625],"iteration":327,"passed_time":0.2722992583,"remaining_time":0.5578814071},
{"learn":[543.2161893],"iteration":328,"passed_time":0.2731397227,"remaining_time":0.5570722004},
{"learn":[542.2288381],"iteration":329,"passed_time":0.273902333,"remaining_time":0.5561047368},
{"learn":[541.7244652],"iteration":330,"passed_time":0.274746001,"remaining_time":0.5553023405},
{"learn":[539.4401227],"iteration":331,"passed_time":0.2757498107,"remaining_time":0.5548219082},
{"learn":[537.7430383],"iteration":332,"passed_time":0.2767685476,"remaining_time":0.5543682319},
{"learn":[536.5974803],"iteration":333,"passed_time":0.2777404382,"remaining_time":0.55381776},
{"learn":[536.1008866],"iteration":334,"passed_time":0.2785773089,"remaining_time":0.5529967476},
{"learn":[534.9645174],"iteration":335,"passed_time":0.2795417712,"remaining_time":0.552427786},
{"learn":[533.9011326],"iteration":336,"passed_time":0.2803919871,"remaining_time":0.5516317134},
{"learn":[532.8061571],"iteration":337,"passed_time":0.2812920825,"remaining_time":0.5509330137},
{"learn":[531.8366482],"iteration":338,"passed_time":0.2822553943,"remaining_time":0.5503563883},
{"learn":[530.2446],"iteration":339,"passed_time":0.2830619171,"remaining_time":0.5494731332},
{"learn":[529.389012],"iteration":340,"passed_time":0.2838912079,"remaining_time":0.5486343285},
{"learn":[528.185112],"iteration":341,"passed_time":0.2847425951,"remaining_time":0.5478380924},
{"learn":[527.1199149],"iteration":342,"passed_time":0.2856801662,"remaining_time":0.5472066157},
{"learn":[526.0740673],"iteration":343,"passed_time":0.2865804718,"remaining_time":0.5465022951},
{"learn":[524.2014115],"iteration":344,"passed_time":0.2874473976,"remaining_time":0.5457334651},
{"learn":[523.1805199],"iteration":345,"passed_time":0.2883150743,"remaining_time":0.5449654873},
{"learn":[522.3602837],"iteration":346,"passed_time":0.2891633979,"remaining_time":0.5441605154},
{"learn":[521.8874934],"iteration":347,"passed_time":0.2900256873,"remaining_time":0.5433814601},
{"learn":[519.7460134],"iteration":348,"passed_time":0.2909627578,"remaining_time":0.5427414192},
{"learn":[518.1323148],"iteration":349,"passed_time":0.2918515093,"remaining_time":0.5420099459},
{"learn":[517.6318511],"iteration":350,"passed_time":0.2928683237,"remaining_time":0.5415143648},
{"learn":[516.1210514],"iteration":351,"passed_time":0.2937874418,"remaining_time":0.5408359724},
{"learn":[514.3583342],"iteration":352,"passed_time":0.2947281463,"remaining_time":0.5401957809},
{"learn":[513.661442],"iteration":353,"passed_time":0.2957793523,"remaining_time":0.5397555412},
{"learn":[511.425923],"iteration":354,"passed_time":0.2966578313,"remaining_time":0.5389980316},
{"learn":[510.7571344],"iteration":355,"passed_time":0.2975454218,"remaining_time":0.5382563249},
{"learn":[510.106077],"iteration":356,"passed_time":0.298501525,"remaining_time":0.5376372005},
{"learn":[508.3968776],"iteration":357,"passed_time":0.2994650262,"remaining_time":0.5370294603},
{"learn":[507.8124207],"iteration":358,"passed_time":0.3003592243,"remaining_time":0.5362959965},
{"learn":[507.3660738],"iteration":359,"passed_time":0.3012864324,"remaining_time":0.5356203242},
{"learn":[506.9314813],"iteration":360,"passed_time":0.3022117376,"remaining_time":0.5349398902},
{"learn":[505.4863254],"iteration":361,"passed_time":0.3031094196,"remaining_time":0.5342094191},
{"learn":[503.2473122],"iteration":362,"passed_time":0.3040207184,"remaining_time":0.5335019219},
{"learn":[502.648496],"iteration":363,"passed_time":0.3049454741,"remaining_time":0.5328168175},
{"learn":[500.5131641],"iteration":364,"passed_time":0.3058795093,"remaining_time":0.5321465436},
{"learn":[500.0765565],"iteration":365,"passed_time":0.3067801053,"remaining_time":0.5314169037},
{"learn":[497.9976916],"iteration":366,"passed_time":0.3076628901,"remaining_time":0.5306556115},
{"learn":[496.3569956],"iteration":367,"passed_time":0.3085518522,"remaining_time":0.5299042679},
{"learn":[494.6749234],"iteration":368,"passed_time":0.3095306016,"remaining_time":0.5293057171},
{"learn":[492.604255],"iteration":369,"passed_time":0.3104042354,"remaining_time":0.5285261305},
{"learn":[491.280906],"iteration":370,"passed_time":0.311401718,"remaining_time":0.5279560125},
{"learn":[490.8378124],"iteration":371,"passed_time":0.3122308386,"remaining_time":0.5270993727},
{"learn":[490.3859135],"iteration":372,"passed_time":0.3130152558,"remaining_time":0.5261677357},
{"learn":[489.1718794],"iteration":373,"passed_time":0.3138438867,"remaining_time":0.5253108906},
{"learn":[488.2149345],"iteration":374,"passed_time":0.3146042852,"remaining_time":0.5243404754},
{"learn":[487.8491299],"iteration":375,"passed_time":0.3154658129,"remaining_time":0.5235390086},
{"learn":[485.8588459],"iteration":376,"passed_time":0.316305707,"remaining_time":0.5227014733},
{"learn":[484.681454],"iteration":377,"passed_time":0.3171539207,"remaining_time":0.5218776155},
{"learn":[483.9130914],"iteration":378,"passed_time":0.3181761412,"remaining_time":0.5213387432},
{"learn":[482.0122314],"iteration":379,"passed_time":0.3191512971,"remaining_time":0.5207205374},
{"learn":[480.1745891],"iteration":380,"passed_time":0.3200394374,"remaining_time":0.519959086},
{"learn":[478.4213224],"iteration":381,"passed_time":0.3209165462,"remaining_time":0.5191791245},
{"learn":[477.2356605],"iteration":382,"passed_time":0.3218897882,"remaining_time":0.518553523},
{"learn":[476.5297984],"iteration":383,"passed_time":0.3228506662,"remaining_time":0.5179062771},
{"learn":[475.4030612],"iteration":384,"passed_time":0.3237695441,"remaining_time":0.5171903107},
{"learn":[474.4143799],"iteration":385,"passed_time":0.3245948802,"remaining_time":0.5163244986},
{"learn":[473.6989314],"iteration":386,"passed_time":0.3253713179,"remaining_time":0.5153814415},
{"learn":[471.8048027],"iteration":387,"passed_time":0.3261764106,"remaining_time":0.5144844415},
{"learn":[470.8410334],"iteration":388,"passed_time":0.3271006649,"remaining_time":0.5137750804},
{"learn":[470.5825668],"iteration":389,"passed_time":0.3279342809,"remaining_time":0.5129228497},
{"learn":[468.9396082],"iteration":390,"passed_time":0.3287210309,"remaining_time":0.5119977182},
{"learn":[468.2500459],"iteration":391,"passed_time":0.3295684428,"remaining_time":0.5111673807},
{"learn":[466.4262659],"iteration":392,"passed_time":0.3305589563,"remaining_time":0.5105579809},
{"learn":[466.1747896],"iteration":393,"passed_time":0.3314276642,"remaining_time":0.5097593008},
{"learn":[465.8339851],"iteration":394,"passed_time":0.3322273697,"remaining_time":0.5088545789},
{"learn":[464.7601202],"iteration":395,"passed_time":0.3331252925,"remaining_time":0.5081001937},
{"learn":[463.8169797],"iteration":396,"passed_time":0.3339325479,"remaining_time":0.5072073712},
{"learn":[462.2577755],"iteration":397,"passed_time":0.3348866678,"remaining_time":0.5065371207},
{"learn":[460.3932178],"iteration":398,"passed_time":0.3358239074,"remaining_time":0.5058400209},
{"learn":[459.6242652],"iteration":399,"passed_time":0.3367326331,"remaining_time":0.5050989497},
{"learn":[459.3807501],"iteration":400,"passed_time":0.3377838694,"remaining_time":0.5045699196},
{"learn":[458.6698929],"iteration":401,"passed_time":0.3386416743,"remaining_time":0.5037505503},
{"learn":[458.3391566],"iteration":402,"passed_time":0.3394868149,"remaining_time":0.5029122295},
{"learn":[457.2564093],"iteration":403,"passed_time":0.3404076142,"remaining_time":0.5021854903},
{"learn":[456.2433196],"iteration":404,"passed_time":0.341299791,"remaining_time":0.5014157423},
{"learn":[454.5346501],"iteration":405,"passed_time":0.3422454701,"remaining_time":0.500723668},
{"learn":[453.5505082],"iteration":406,"passed_time":0.3430538459,"remaining_time":0.4998302964},
{"learn":[452.8795168],"iteration":407,"passed_time":0.3440374911,"remaining_time":0.4991916538},
{"learn":[452.5546684],"iteration":408,"passed_time":0.3448720574,"remaining_time":0.498335907},
{"learn":[451.4409294],"iteration":409,"passed_time":0.3456891237,"remaining_time":0.4974550804},
{"learn":[450.8529496],"iteration":410,"passed_time":0.3464459688,"remaining_time":0.4964882618},
{"learn":[449.3691479],"iteration":411,"passed_time":0.3472328489,"remaining_time":0.4955653281},
{"learn":[448.4221375],"iteration":412,"passed_time":0.3481035985,"remaining_time":0.4947622574},
{"learn":[448.1082059],"iteration":413,"passed_time":0.348985533,"remaining_time":0.4939746917},
{"learn":[447.0193464],"iteration":414,"passed_time":0.3500950384,"remaining_time":0.4935074637},
{"learn":[446.4495003],"iteration":415,"passed_time":0.3510246894,"remaining_time":0.4927846601},
{"learn":[445.5263238],"iteration":416,"passed_time":0.3519156539,"remaining_time":0.4920067775},
{"learn":[444.90153],"iteration":417,"passed_time":0.3529051853,"remaining_time":0.491365593},
{"learn":[444.3402873],"iteration":418,"passed_time":0.3537002962,"remaining_time":0.4904531553},
{"learn":[444.040238],"iteration":419,"passed_time":0.3546693248,"remaining_time":0.4897814485},
{"learn":[443.179598],"iteration":420,"passed_time":0.3555388128,"remaining_time":0.4889714314},
{"learn":[442.3404921],"iteration":421,"passed_time":0.3565259222,"remaining_time":0.4883222347},
{"learn":[440.6064822],"iteration":422,"passed_time":0.3575057228,"remaining_time":0.4876614706},
{"learn":[439.7889488],"iteration":423,"passed_time":0.3582806387,"remaining_time":0.4867208677},
{"learn":[439.2603922],"iteration":424,"passed_time":0.359101829,"remaining_time":0.485843651},
{"learn":[438.338221],"iteration":425,"passed_time":0.3598943976,"remaining_time":0.484928132},
{"learn":[437.818878],"iteration":426,"passed_time":0.3607617923,"remaining_time":0.4841135995},
{"learn":[437.0346413],"iteration":427,"passed_time":0.3616616374,"remaining_time":0.4833421884},
{"learn":[436.15202],"iteration":428,"passed_time":0.3626008396,"remaining_time":0.4826225627},
{"learn":[435.3984992],"iteration":429,"passed_time":0.363515852,"remaining_time":0.4818698503},
{"learn":[434.284002],"iteration":430,"passed_time":0.3643721559,"remaining_time":0.4810388787},
{"learn":[432.9708941],"iteration":431,"passed_time":0.3651634213,"remaining_time":0.4801222762},
{"learn":[432.3125685],"iteration":432,"passed_time":0.3660450439,"remaining_time":0.4793245724},
{"learn":[431.7884352],"iteration":433,"passed_time":0.3668797428,"remaining_time":0.4784652867},
{"learn":[430.9419069],"iteration":434,"passed_time":0.368111905,"remaining_time":0.4781223594},
{"learn":[430.3112723],"iteration":435,"passed_time":0.369110378,"remaining_time":0.4774730577},
{"learn":[429.7606923],"iteration":436,"passed_time":0.37017574,"remaining_time":0.4769083332},
{"learn":[429.2570462],"iteration":437,"passed_time":0.3711665046,"remaining_time":0.4762456064},
{"learn":[428.3780215],"iteration":438,"passed_time":0.3721030536,"remaining_time":0.4755121026},
{"learn":[427.8847326],"iteration":439,"passed_time":0.373179619,"remaining_time":0.4749558787},
{"learn":[427.0804685],"iteration":440,"passed_time":0.3740937821,"remaining_time":0.474191438},
{"learn":[426.5970937],"iteration":441,"passed_time":0.3749226416,"remaining_time":0.4733186289},
{"learn":[426.1312581],"iteration":442,"passed_time":0.3757550861,"remaining_time":0.4724505259},
{"learn":[425.3763373],"iteration":443,"passed_time":0.3765590272,"remaining_time":0.47154689},
{"learn":[424.5318458],"iteration":444,"passed_time":0.3774042371,"remaining_time":0.4706951721},
{"learn":[424.2078232],"iteration":445,"passed_time":0.3781908772,"remaining_time":0.4697707309},
{"learn":[423.6575595],"iteration":446,"passed_time":0.3789448881,"remaining_time":0.4688065394},
{"learn":[422.074048],"iteration":447,"passed_time":0.3798258198,"remaining_time":0.4679996708},
{"learn":[420.9557448],"iteration":448,"passed_time":0.3806810817,"remaining_time":0.4671609711},
{"learn":[420.0754659],"iteration":449,"passed_time":0.3815428914,"remaining_time":0.4663302005},
{"learn":[419.6219784],"iteration":450,"passed_time":0.3824755165,"remaining_time":0.4655854957},
{"learn":[419.2046523],"iteration":451,"passed_time":0.3834279136,"remaining_time":0.4648639306},
{"learn":[418.706906],"iteration":452,"passed_time":0.3842548616,"remaining_time":0.463989866},
{"learn":[418.2331249],"iteration":453,"passed_time":0.385134423,"remaining_time":0.4631792841},
{"learn":[417.3659771],"iteration":454,"passed_time":0.3861165267,"remaining_time":0.4624912243},
{"learn":[416.8979865],"iteration":455,"passed_time":0.3871135187,"remaining_time":0.4618196364},
{"learn":[416.3558323],"iteration":456,"passed_time":0.3879765182,"remaining_time":0.4609874166},
{"learn":[415.831796],"iteration":457,"passed_time":0.3890392988,"remaining_time":0.4603914846},
{"learn":[414.5738226],"iteration":458,"passed_time":0.3900914451,"remaining_time":0.4597809843},
{"learn":[414.0654584],"iteration":459,"passed_time":0.3910137278,"remaining_time":0.4590161153},
{"learn":[413.5270418],"iteration":460,"passed_time":0.3917597692,"remaining_time":0.4580445024},
{"learn":[413.0348763],"iteration":461,"passed_time":0.3927374265,"remaining_time":0.4573435832},
{"learn":[412.3320149],"iteration":462,"passed_time":0.3935422689,"remaining_time":0.4564410333},
{"learn":[411.6987232],"iteration":463,"passed_time":0.394444456,"remaining_time":0.4556513544},
{"learn":[410.9055971],"iteration":464,"passed_time":0.3954281521,"remaining_time":0.4549549708},
{"learn":[410.0506172],"iteration":465,"passed_time":0.3965863551,"remaining_time":0.4544573254},
{"learn":[409.6602455],"iteration":466,"passed_time":0.3975462428,"remaining_time":0.4537305084},
{"learn":[409.1807732],"iteration":467,"passed_time":0.3983338438,"remaining_time":0.4528068481},
{"learn":[408.7993386],"iteration":468,"passed_time":0.3992831378,"remaining_time":0.4520668361},
{"learn":[408.1191545],"iteration":469,"passed_time":0.400074753,"remaining_time":0.4511481257},
{"learn":[407.7444795],"iteration":470,"passed_time":0.4010310272,"remaining_time":0.4504148905},
{"learn":[407.0655466],"iteration":471,"passed_time":0.4022587132,"remaining_time":0.4499843233},
{"learn":[406.5768361],"iteration":472,"passed_time":0.4031206228,"remaining_time":0.4491428503},
{"learn":[406.06842],"iteration":473,"passed_time":0.4040188754,"remaining_time":0.4483416212},
{"learn":[405.3730395],"iteration":474,"passed_time":0.4048943122,"remaining_time":0.4475147661},
{"learn":[404.3077154],"iteration":475,"passed_time":0.4057889503,"remaining_time":0.4467088444},
{"learn":[403.6593156],"iteration":476,"passed_time":0.4066959548,"remaining_time":0.4459161098},
{"learn":[403.3688019],"iteration":477,"passed_time":0.4074485331,"remaining_time":0.4449542559},
{"learn":[402.8975332],"iteration":478,"passed_time":0.4084258817,"remaining_time":0.4442377544},
{"learn":[402.045385],"iteration":479,"passed_time":0.4093926076,"remaining_time":0.4435086582},
{"learn":[400.5417447],"iteration":480,"passed_time":0.4103272935,"remaining_time":0.4427440027},
{"learn":[399.8960367],"iteration":481,"passed_time":0.4111411751,"remaining_time":0.4418488147},
{"learn":[399.4224393],"iteration":482,"passed_time":0.4121684132,"remaining_time":0.4411823388},
{"learn":[398.5015908],"iteration":483,"passed_time":0.413051067,"remaining_time":0.4403602284},
{"learn":[396.9945791],"iteration":484,"passed_time":0.4139721975,"remaining_time":0.4395787252},
{"learn":[396.207338],"iteration":485,"passed_time":0.4149881622,"remaining_time":0.4388969452},
{"learn":[395.7447462],"iteration":486,"passed_time":0.4158158211,"remaining_time":0.4380154337},
{"learn":[394.8845507],"iteration":487,"passed_time":0.4167134544,"remaining_time":0.4372075587},
{"learn":[394.4725417],"iteration":488,"passed_time":0.4176763749,"remaining_time":0.4364675411},
{"learn":[393.6042074],"iteration":489,"passed_time":0.4186154169,"remaining_time":0.4357017604},
{"learn":[393.0190877],"iteration":490,"passed_time":0.4194067015,"remaining_time":0.4347820999},
{"learn":[392.6049206],"iteration":491,"passed_time":0.4202869732,"remaining_time":0.4339548422},
{"learn":[391.7564607],"iteration":492,"passed_time":0.4212400427,"remaining_time":0.4332022346},
{"learn":[391.5179108],"iteration":493,"passed_time":0.4222721356,"remaining_time":0.4325297583},
{"learn":[390.9436633],"iteration":494,"passed_time":0.4231636508,"remaining_time":0.4317124114},
{"learn":[390.4002532],"iteration":495,"passed_time":0.4240436516,"remaining_time":0.4308830654},
{"learn":[390.1683364],"iteration":496,"passed_time":0.4249560518,"remaining_time":0.4300863059},
{"learn":[389.3375914],"iteration":497,"passed_time":0.425829945,"remaining_time":0.4292502659},
{"learn":[389.0041977],"iteration":498,"passed_time":0.4267693074,"remaining_time":0.4284798056},
{"learn":[387.9870797],"iteration":499,"passed_time":0.4276230483,"remaining_time":0.4276230483},
{"learn":[387.4464848],"iteration":500,"passed_time":0.4286543204,"remaining_time":0.4269431255},
{"learn":[386.6372812],"iteration":501,"passed_time":0.4295494791,"remaining_time":0.4261267741},
{"learn":[385.7648872],"iteration":502,"passed_time":0.4304409648,"remaining_time":0.4253064801},
{"learn":[385.5411682],"iteration":503,"passed_time":0.4312913508,"remaining_time":0.4244454564},
{"learn":[384.7503554],"iteration":504,"passed_time":0.4321132222,"remaining_time":0.4235565248},
{"learn":[384.2541465],"iteration":505,"passed_time":0.4329363262,"remaining_time":0.4226690616},
{"learn":[383.5702731],"iteration":506,"passed_time":0.4339033216,"remaining_time":0.4219217703},
{"learn":[382.9594776],"iteration":507,"passed_time":0.4348018652,"remaining_time":0.4211073182},
{"learn":[382.7424496],"iteration":508,"passed_time":0.4357715832,"remaining_time":0.4203611932},
{"learn":[381.9541269],"iteration":509,"passed_time":0.4365458383,"remaining_time":0.4194263936},
{"learn":[381.0161332],"iteration":510,"passed_time":0.4373078687,"remaining_time":0.4184805241},
{"learn":[380.4474281],"iteration":511,"passed_time":0.4380758764,"remaining_time":0.4175410696},
{"learn":[379.8683582],"iteration":512,"passed_time":0.4388681635,"remaining_time":0.4166253326},
{"learn":[379.1581088],"iteration":513,"passed_time":0.4396215537,"remaining_time":0.4156732978},
{"learn":[378.6511687],"iteration":514,"passed_time":0.4405422131,"remaining_time":0.4148795599},
{"learn":[378.0321989],"iteration":515,"passed_time":0.4414450418,"remaining_time":0.4140686051},
{"learn":[377.4627471],"iteration":516,"passed_time":0.4422477915,"remaining_time":0.4131637974},
{"learn":[377.2154358],"iteration":517,"passed_time":0.4431701535,"remaining_time":0.4123706834},
{"learn":[376.8613327],"iteration":518,"passed_time":0.4441683962,"remaining_time":0.4116473961},
{"learn":[376.4961929],"iteration":519,"passed_time":0.4449659085,"remaining_time":0.4107377617},
{"learn":[376.2579441],"iteration":520,"passed_time":0.4457591168,"remaining_time":0.4098246006},
{"learn":[375.9376001],"iteration":521,"passed_time":0.4467593012,"remaining_time":0.4091014291},
{"learn":[375.1615265],"iteration":522,"passed_time":0.4476426266,"remaining_time":0.4082706174},
{"learn":[374.4361036],"iteration":523,"passed_time":0.4484769835,"remaining_time":0.4073951224},
{"learn":[373.8171878],"iteration":524,"passed_time":0.4493910556,"remaining_time":0.4065919075},
{"learn":[372.9607814],"iteration":525,"passed_time":0.4501670127,"remaining_time":0.4056638099},
{"learn":[372.7295815],"iteration":526,"passed_time":0.4508983265,"remaining_time":0.4046962209},
{"learn":[372.3958278],"iteration":527,"passed_time":0.4516189274,"remaining_time":0.4037199503},
{"learn":[371.7082672],"iteration":528,"passed_time":0.4523682527,"remaining_time":0.4027702212},
{"learn":[371.0248909],"iteration":529,"passed_time":0.4531922681,"remaining_time":0.401887483},
{"learn":[370.404769],"iteration":530,"passed_time":0.4540353662,"remaining_time":0.4010218207},
{"learn":[369.6617044],"iteration":531,"passed_time":0.4548737463,"remaining_time":0.4001520926},
{"learn":[369.4377033],"iteration":532,"passed_time":0.4556583437,"remaining_time":0.3992353593},
{"learn":[368.790925],"iteration":533,"passed_time":0.4565039649,"remaining_time":0.3983723738},
{"learn":[368.4706451],"iteration":534,"passed_time":0.4572813929,"remaining_time":0.3974501826},
{"learn":[368.2548106],"iteration":535,"passed_time":0.4580118456,"remaining_time":0.3964878664},
{"learn":[367.6823866],"iteration":536,"passed_time":0.4588932195,"remaining_time":0.3956565375},
{"learn":[367.3554664],"iteration":537,"passed_time":0.4597776154,"remaining_time":0.3948276176},
{"learn":[366.2519771],"iteration":538,"passed_time":0.4605734454,"remaining_time":0.3939227427},
{"learn":[366.0412912],"iteration":539,"passed_time":0.4613607477,"remaining_time":0.3930110073},
{"learn":[365.5953782],"iteration":540,"passed_time":0.4622397971,"remaining_time":0.3921775728},
{"learn":[365.2269243],"iteration":541,"passed_time":0.4630303116,"remaining_time":0.3912691563},
{"learn":[364.6043823],"iteration":542,"passed_time":0.4638796272,"remaining_time":0.3904106623},
{"learn":[364.4000845],"iteration":543,"passed_time":0.4646020103,"remaining_time":0.3894458028},
{"learn":[364.130027],"iteration":544,"passed_time":0.465359205,"remaining_time":0.3885108959},
{"learn":[363.4354289],"iteration":545,"passed_time":0.4661408981,"remaining_time":0.3875970105},
{"learn":[362.45239],"iteration":546,"passed_time":0.4668934673,"remaining_time":0.3866594894},
{"learn":[362.310377],"iteration":547,"passed_time":0.4677499214,"remaining_time":0.3858083293},
{"learn":[362.0563999],"iteration":548,"passed_time":0.4685678278,"remaining_time":0.3849254833},
{"learn":[361.2946589],"iteration":549,"passed_time":0.4693813898,"remaining_time":0.384039319},
{"learn":[361.0335947],"iteration":550,"passed_time":0.4702427598,"remaining_time":0.383192376},
{"learn":[360.4759956],"iteration":551,"passed_time":0.4711784478,"remaining_time":0.3824056967},
{"learn":[359.8523229],"iteration":552,"passed_time":0.4720811463,"remaining_time":0.3815918127},
{"learn":[359.3016873],"iteration":553,"passed_time":0.4729951976,"remaining_time":0.3807867475},
{"learn":[358.5607909],"iteration":554,"passed_time":0.4737848819,"remaining_time":0.379881572},
{"learn":[358.2601842],"iteration":555,"passed_time":0.4746046005,"remaining_time":0.3790007961},
{"learn":[357.9251744],"iteration":556,"passed_time":0.4754156003,"remaining_time":0.3781133051},
{"learn":[357.7368046],"iteration":557,"passed_time":0.4763178783,"remaining_time":0.3772983911},
{"learn":[357.3808339],"iteration":558,"passed_time":0.4771547173,"remaining_time":0.3764315391},
{"learn":[356.6314229],"iteration":559,"passed_time":0.4778843791,"remaining_time":0.3754805836},
{"learn":[356.0824585],"iteration":560,"passed_time":0.478653458,"remaining_time":0.3745612621},
{"learn":[355.8446101],"iteration":561,"passed_time":0.4794950836,"remaining_time":0.3736990153},
{"learn":[355.1874745],"iteration":562,"passed_time":0.4802915252,"remaining_time":0.37280177},
{"learn":[354.6629014],"iteration":563,"passed_time":0.481051494,"remaining_time":0.3718766868},
{"learn":[353.968139],"iteration":564,"passed_time":0.4820312838,"remaining_time":0.3711214309},
{"learn":[353.5410728],"iteration":565,"passed_time":0.4828080619,"remaining_time":0.3702097153},
{"learn":[352.8998231],"iteration":566,"passed_time":0.4838256577,"remaining_time":0.3694823806},
{"learn":[352.3756733],"iteration":567,"passed_time":0.484703867,"remaining_time":0.3686480115},
{"learn":[351.8882281],"iteration":568,"passed_time":0.4855801031,"remaining_time":0.3678119937},
{"learn":[351.6444138],"iteration":569,"passed_time":0.4864316405,"remaining_time":0.3669572025},
{"learn":[350.7280508],"iteration":570,"passed_time":0.487327681,"remaining_time":0.3661358584},
{"learn":[350.4890292],"iteration":571,"passed_time":0.4882036084,"remaining_time":0.3652992035},
{"learn":[349.718635],"iteration":572,"passed_time":0.4890573282,"remaining_time":0.3644458623},
{"learn":[349.3994913],"iteration":573,"passed_time":0.4898599265,"remaining_time":0.3635545796},
{"learn":[348.9990392],"iteration":574,"passed_time":0.4907433329,"remaining_time":0.362723333},
{"learn":[348.3316222],"iteration":575,"passed_time":0.4914956317,"remaining_time":0.3617953956},
{"learn":[347.7588519],"iteration":576,"passed_time":0.492246619,"remaining_time":0.3608671054},
{"learn":[347.5964183],"iteration":577,"passed_time":0.4929451736,"remaining_time":0.3599011475},
{"learn":[347.3148561],"iteration":578,"passed_time":0.4936702599,"remaining_time":0.3589554049},
{"learn":[346.8836049],"iteration":579,"passed_time":0.4944504613,"remaining_time":0.358050334},
{"learn":[346.6536483],"iteration":580,"passed_time":0.4952297223,"remaining_time":0.3571450149},
{"learn":[346.4967764],"iteration":581,"passed_time":0.4960375475,"remaining_time":0.3562606441},
{"learn":[346.2648117],"iteration":582,"passed_time":0.4970523708,"remaining_time":0.3555245946},
{"learn":[345.7093941],"iteration":583,"passed_time":0.4979925233,"remaining_time":0.3547344001},
{"learn":[344.9916903],"iteration":584,"passed_time":0.498808358,"remaining_time":0.3538555018},
{"learn":[344.8398613],"iteration":585,"passed_time":0.4996527586,"remaining_time":0.3529970001},
{"learn":[344.42293],"iteration":586,"passed_time":0.5005308769,"remaining_time":0.3521622694},
{"learn":[343.8774469],"iteration":587,"passed_time":0.5013404951,"remaining_time":0.3512793945},
{"learn":[343.5504605],"iteration":588,"passed_time":0.5021271241,"remaining_time":0.3503807267},
{"learn":[343.2314536],"iteration":589,"passed_time":0.5029214832,"remaining_time":0.3494878103},
{"learn":[343.0750957],"iteration":590,"passed_time":0.5037370968,"remaining_time":0.3486099367},
{"learn":[342.6086004],"iteration":591,"passed_time":0.5045886142,"remaining_time":0.3477570179},
{"learn":[342.1081342],"iteration":592,"passed_time":0.5053566819,"remaining_time":0.3468468289},
{"learn":[341.4668213],"iteration":593,"passed_time":0.5061101822,"remaining_time":0.3459271615},
{"learn":[341.0905465],"iteration":594,"passed_time":0.5068496557,"remaining_time":0.3449985051},
{"learn":[340.4679095],"iteration":595,"passed_time":0.5075920126,"remaining_time":0.3440724381},
{"learn":[340.166468],"iteration":596,"passed_time":0.5083390652,"remaining_time":0.3431501562},
{"learn":[339.4283605],"iteration":597,"passed_time":0.5091163539,"remaining_time":0.3422487864},
{"learn":[339.1097299],"iteration":598,"passed_time":0.5098812378,"remaining_time":0.3413395265},
{"learn":[338.9460862],"iteration":599,"passed_time":0.5106040013,"remaining_time":0.3404026676},
{"learn":[338.2541229],"iteration":600,"passed_time":0.5113428341,"remaining_time":0.3394771894},
{"learn":[337.9939996],"iteration":601,"passed_time":0.5122049241,"remaining_time":0.3386338203},
{"learn":[337.4807305],"iteration":602,"passed_time":0.5131108974,"remaining_time":0.3378192807},
{"learn":[337.1737469],"iteration":603,"passed_time":0.5138707352,"remaining_time":0.3369086277},
{"learn":[336.5694395],"iteration":604,"passed_time":0.514634819,"remaining_time":0.3360012454},
{"learn":[336.245735],"iteration":605,"passed_time":0.5153879989,"remaining_time":0.3350872468},
{"learn":[335.9568233],"iteration":606,"passed_time":0.516107879,"remaining_time":0.3341522182},
{"learn":[335.5192923],"iteration":607,"passed_time":0.5168883415,"remaining_time":0.333256957},
{"learn":[334.833338],"iteration":608,"passed_time":0.5176585117,"remaining_time":0.3323554648},
{"learn":[334.6933773],"iteration":609,"passed_time":0.5184110508,"remaining_time":0.3314431308},
{"learn":[334.540784],"iteration":610,"passed_time":0.5191246133,"remaining_time":0.3305065051},
{"learn":[333.837677],"iteration":611,"passed_time":0.5199097506,"remaining_time":0.3296159857},
{"learn":[333.2258563],"iteration":612,"passed_time":0.5206429566,"remaining_time":0.3286930248},
{"learn":[332.6315264],"iteration":613,"passed_time":0.521359743,"remaining_time":0.3277603596},
{"learn":[332.2736532],"iteration":614,"passed_time":0.5220843087,"remaining_time":0.3268332664},
{"learn":[331.9872158],"iteration":615,"passed_time":0.5228494929,"remaining_time":0.3259321514},
{"learn":[331.4166393],"iteration":616,"passed_time":0.5236242987,"remaining_time":0.3250374496},
{"learn":[331.0299029],"iteration":617,"passed_time":0.524356914,"remaining_time":0.3241170569},
{"learn":[330.4011058],"iteration":618,"passed_time":0.5251021144,"remaining_time":0.3232050171},
{"learn":[329.9613299],"iteration":619,"passed_time":0.5258386143,"remaining_time":0.322288183},
{"learn":[329.7074704],"iteration":620,"passed_time":0.5267693355,"remaining_time":0.321490464},
{"learn":[329.2646704],"iteration":621,"passed_time":0.5275892351,"remaining_time":0.3206249692},
{"learn":[329.0270632],"iteration":622,"passed_time":0.5283274371,"remaining_time":0.3197101826},
{"learn":[328.5616687],"iteration":623,"passed_time":0.5291163697,"remaining_time":0.3188265305},
{"learn":[327.9127787],"iteration":624,"passed_time":0.5298388229,"remaining_time":0.3179032937},
{"learn":[327.4473659],"iteration":625,"passed_time":0.5305865463,"remaining_time":0.316995796},
{"learn":[327.1699832],"iteration":626,"passed_time":0.5314073369,"remaining_time":0.3161322754},
{"learn":[326.8949471],"iteration":627,"passed_time":0.5321453087,"remaining_time":0.3152198325},
{"learn":[326.2322993],"iteration":628,"passed_time":0.532872908,"remaining_time":0.3143018265},
{"learn":[325.7871315],"iteration":629,"passed_time":0.533596052,"remaining_time":0.3133818083},
{"learn":[325.6408104],"iteration":630,"passed_time":0.5342925241,"remaining_time":0.3124468168},
{"learn":[325.2536292],"iteration":631,"passed_time":0.5350420697,"remaining_time":0.3115434836},
{"learn":[325.091248],"iteration":632,"passed_time":0.5357841663,"remaining_time":0.3106363176},
{"learn":[324.7033049],"iteration":633,"passed_time":0.5365324804,"remaining_time":0.3097332616},
{"learn":[324.4417114],"iteration":634,"passed_time":0.5372690304,"remaining_time":0.3088239309},
{"learn":[324.00243],"iteration":635,"passed_time":0.5380103561,"remaining_time":0.3079178768},
{"learn":[323.5769752],"iteration":636,"passed_time":0.5387475069,"remaining_time":0.3070099608},
{"learn":[323.1591902],"iteration":637,"passed_time":0.5394828655,"remaining_time":0.3061015632},
{"learn":[322.7932453],"iteration":638,"passed_time":0.540341201,"remaining_time":0.3052631824},
{"learn":[322.4165943],"iteration":639,"passed_time":0.5411982258,"remaining_time":0.304424002},
{"learn":[322.2755151],"iteration":640,"passed_time":0.5419653724,"remaining_time":0.3035344285},
{"learn":[321.7744512],"iteration":641,"passed_time":0.5427953841,"remaining_time":0.3026802921},
{"learn":[321.5528974],"iteration":642,"passed_time":0.5437459698,"remaining_time":0.3018931745},
{"learn":[321.2818454],"iteration":643,"passed_time":0.5445315476,"remaining_time":0.3010143338},
{"learn":[321.0511259],"iteration":644,"passed_time":0.5453516374,"remaining_time":0.3001547772},
{"learn":[320.6321602],"iteration":645,"passed_time":0.5461596745,"remaining_time":0.2992887381},
{"learn":[320.4214302],"iteration":646,"passed_time":0.5469437505,"remaining_time":0.2984098051},
{"learn":[320.0311815],"iteration":647,"passed_time":0.5477088855,"remaining_time":0.2975208761},
{"learn":[319.9072173],"iteration":648,"passed_time":0.5485326789,"remaining_time":0.2966640529},
{"learn":[319.2137939],"iteration":649,"passed_time":0.5493681772,"remaining_time":0.2958136339},
{"learn":[318.7364473],"iteration":650,"passed_time":0.5501858333,"remaining_time":0.2949536956},
{"learn":[318.4540102],"iteration":651,"passed_time":0.5509911163,"remaining_time":0.2940872829},
{"learn":[317.7700254],"iteration":652,"passed_time":0.5517859951,"remaining_time":0.2932155288},
{"learn":[317.5464419],"iteration":653,"passed_time":0.5526497279,"remaining_time":0.2923804371},
{"learn":[317.3008018],"iteration":654,"passed_time":0.5535236621,"remaining_time":0.2915506312},
{"learn":[316.6612343],"iteration":655,"passed_time":0.5543210248,"remaining_time":0.2906805374},
{"learn":[316.5389234],"iteration":656,"passed_time":0.5551660336,"remaining_time":0.2898355396},
{"learn":[316.2982484],"iteration":657,"passed_time":0.5561171499,"remaining_time":0.2890456919},
{"learn":[315.9059598],"iteration":658,"passed_time":0.5569995951,"remaining_time":0.2882198208},
{"learn":[315.5615903],"iteration":659,"passed_time":0.5579172807,"remaining_time":0.2874119325},
{"learn":[314.901116],"iteration":660,"passed_time":0.5587861405,"remaining_time":0.2865786711},
{"learn":[314.5219589],"iteration":661,"passed_time":0.5596168614,"remaining_time":0.2857258295},
{"learn":[314.4013695],"iteration":662,"passed_time":0.5604601589,"remaining_time":0.2848794473},
{"learn":[314.1697161],"iteration":663,"passed_time":0.561273051,"remaining_time":0.2840176885},
{"learn":[313.9267993],"iteration":664,"passed_time":0.5620628246,"remaining_time":0.2831444304},
{"learn":[313.753107],"iteration":665,"passed_time":0.5628790991,"remaining_time":0.2822847133},
{"learn":[313.1093867],"iteration":666,"passed_time":0.563722007,"remaining_time":0.2814384233},
{"learn":[312.8467891],"iteration":667,"passed_time":0.5644848084,"remaining_time":0.2805523299},
{"learn":[312.45046],"iteration":668,"passed_time":0.5653255437,"remaining_time":0.2797051644},
{"learn":[312.3333738],"iteration":669,"passed_time":0.5660896049,"remaining_time":0.2788202532},
{"learn":[312.0992342],"iteration":670,"passed_time":0.5668494528,"remaining_time":0.2779336363},
{"learn":[311.729611],"iteration":671,"passed_time":0.5676221577,"remaining_time":0.2770536722},
{"learn":[311.3353217],"iteration":672,"passed_time":0.5684390237,"remaining_time":0.276195484},
{"learn":[311.1415618],"iteration":673,"passed_time":0.5692918117,"remaining_time":0.2753547932},
{"learn":[310.932231],"iteration":674,"passed_time":0.5700881941,"remaining_time":0.2744869083},
{"learn":[310.4228062],"iteration":675,"passed_time":0.5710773851,"remaining_time":0.2737116461},
{"learn":[310.2041717],"iteration":676,"passed_time":0.571919432,"remaining_time":0.2728655488},
{"learn":[310.0915254],"iteration":677,"passed_time":0.5727826842,"remaining_time":0.2720295344},
{"learn":[309.9843059],"iteration":678,"passed_time":0.5735295466,"remaining_time":0.271138416},
{"learn":[309.7847285],"iteration":679,"passed_time":0.5743282217,"remaining_time":0.2702721043},
{"learn":[309.6782278],"iteration":680,"passed_time":0.5751115167,"remaining_time":0.2693987868},
{"learn":[309.3160223],"iteration":681,"passed_time":0.5759422493,"remaining_time":0.2685478523},
{"learn":[309.1015687],"iteration":682,"passed_time":0.5768220913,"remaining_time":0.2677197701},
{"learn":[308.9988954],"iteration":683,"passed_time":0.5775804975,"remaining_time":0.2668354345},
{"learn":[308.3769766],"iteration":684,"passed_time":0.5784415754,"remaining_time":0.2659986807},
{"learn":[308.1013109],"iteration":685,"passed_time":0.5792836315,"remaining_time":0.2651531491},
{"learn":[307.9449947],"iteration":686,"passed_time":0.5801193397,"remaining_time":0.2643047356},
{"learn":[307.3282175],"iteration":687,"passed_time":0.5811437832,"remaining_time":0.2635419482},
{"learn":[306.7237299],"iteration":688,"passed_time":0.5820517786,"remaining_time":0.2627258391},
{"learn":[306.4975316],"iteration":689,"passed_time":0.5829562186,"remaining_time":0.2619078663},
{"learn":[306.1620616],"iteration":690,"passed_time":0.5839545723,"remaining_time":0.2611316394},
{"learn":[305.5838612],"iteration":691,"passed_time":0.5847136192,"remaining_time":0.2602482583},
{"learn":[305.0224515],"iteration":692,"passed_time":0.5855293029,"remaining_time":0.2593903261},
{"learn":[304.526446],"iteration":693,"passed_time":0.5863523271,"remaining_time":0.2585357523},
{"learn":[304.1994198],"iteration":694,"passed_time":0.587117231,"remaining_time":0.2576557632},
{"learn":[303.5853118],"iteration":695,"passed_time":0.5878857893,"remaining_time":0.2567777011},
{"learn":[303.2430565],"iteration":696,"passed_time":0.5888841029,"remaining_time":0.2559998324},
{"learn":[303.1093729],"iteration":697,"passed_time":0.589664245,"remaining_time":0.2551269369},
{"learn":[302.7920342],"iteration":698,"passed_time":0.5904217784,"remaining_time":0.2542445712},
{"learn":[302.4074157],"iteration":699,"passed_time":0.5911706131,"remaining_time":0.2533588342},
{"learn":[302.3095586],"iteration":700,"passed_time":0.5919225332,"remaining_time":0.2524748037},
{"learn":[301.9668191],"iteration":701,"passed_time":0.592737456,"remaining_time":0.2516178944},
{"learn":[301.8163872],"iteration":702,"passed_time":0.5934965429,"remaining_time":0.2507375153},
{"learn":[301.384286],"iteration":703,"passed_time":0.5943535277,"remaining_time":0.2498986423},
{"learn":[301.1751257],"iteration":704,"passed_time":0.5951774713,"remaining_time":0.2490458922},
{"learn":[300.8463694],"iteration":705,"passed_time":0.5960447075,"remaining_time":0.2482112521},
{"learn":[300.6028452],"iteration":706,"passed_time":0.5969162688,"remaining_time":0.2473783122},
{"learn":[300.4324763],"iteration":707,"passed_time":0.5976681071,"remaining_time":0.246495886},
{"learn":[300.0226951],"iteration":708,"passed_time":0.5984149794,"remaining_time":0.2456117899},
{"learn":[299.6057779],"iteration":709,"passed_time":0.5991480052,"remaining_time":0.2447224247},
{"learn":[299.2958934],"iteration":710,"passed_time":0.599887679,"remaining_time":0.2438362015},
{"learn":[299.0823932],"iteration":711,"passed_time":0.6007170599,"remaining_time":0.2429866759},
{"learn":[298.8418455],"iteration":712,"passed_time":0.6017109783,"remaining_time":0.2422034373},
{"learn":[298.7223381],"iteration":713,"passed_time":0.6025482779,"remaining_time":0.2413568732},
{"learn":[298.3214323],"iteration":714,"passed_time":0.6034077239,"remaining_time":0.2405191627},
{"learn":[298.229278],"iteration":715,"passed_time":0.6041843226,"remaining_time":0.2396485302},
{"learn":[297.6777431],"iteration":716,"passed_time":0.6050305136,"remaining_time":0.2388056281},
{"learn":[297.5902415],"iteration":717,"passed_time":0.6058155315,"remaining_time":0.2379386907},
{"learn":[297.3427831],"iteration":718,"passed_time":0.6066932903,"remaining_time":0.2371082261},
{"learn":[297.1032631],"iteration":719,"passed_time":0.6074800495,"remaining_time":0.2362422415},
{"learn":[296.4310894],"iteration":720,"passed_time":0.6083381664,"remaining_time":0.2354040894},
{"learn":[296.0417467],"iteration":721,"passed_time":0.6091828948,"remaining_time":0.2345607268},
{"learn":[295.8306784],"iteration":722,"passed_time":0.6100211564,"remaining_time":0.2337148829},
{"learn":[295.6244625],"iteration":723,"passed_time":0.6108066641,"remaining_time":0.2328489493},
{"learn":[295.3296259],"iteration":724,"passed_time":0.6115432041,"remaining_time":0.2319646636},
{"learn":[295.0197374],"iteration":725,"passed_time":0.6122827977,"remaining_time":0.2310819374},
{"learn":[294.8272694],"iteration":726,"passed_time":0.613110938,"remaining_time":0.2302328557},
{"learn":[294.7393273],"iteration":727,"passed_time":0.6138463767,"remaining_time":0.2293491957},
{"learn":[294.6653552],"iteration":728,"passed_time":0.614593239,"remaining_time":0.228470189},
{"learn":[294.503027],"iteration":729,"passed_time":0.6153076827,"remaining_time":0.2275795539},
{"learn":[294.1196352],"iteration":730,"passed_time":0.6161796044,"remaining_time":0.226747351},
{"learn":[293.5937751],"iteration":731,"passed_time":0.6170344157,"remaining_time":0.2259087752},
{"learn":[293.4076029],"iteration":732,"passed_time":0.617886835,"remaining_time":0.2250692837},
{"learn":[292.6033175],"iteration":733,"passed_time":0.6187121411,"remaining_time":0.2242199312},
{"learn":[292.4053264],"iteration":734,"passed_time":0.6195378376,"remaining_time":0.223370785},
{"learn":[292.3329111],"iteration":735,"passed_time":0.620361551,"remaining_time":0.2225209911},
{"learn":[292.0399613],"iteration":736,"passed_time":0.6212172225,"remaining_time":0.2216826723},
{"learn":[291.3877501],"iteration":737,"passed_time":0.6221762275,"remaining_time":0.2208809913},
{"learn":[290.9598847],"iteration":738,"passed_time":0.6230977585,"remaining_time":0.2200656495},
{"learn":[290.1809415],"iteration":739,"passed_time":0.6239867423,"remaining_time":0.2192385851},
{"learn":[290.0507778],"iteration":740,"passed_time":0.6248161424,"remaining_time":0.2183905275},
{"learn":[289.763942],"iteration":741,"passed_time":0.6255677504,"remaining_time":0.2175154712},
{"learn":[289.5843001],"iteration":742,"passed_time":0.626289723,"remaining_time":0.2166304964},
{"learn":[288.9468379],"iteration":743,"passed_time":0.6270268538,"remaining_time":0.2157511755},
{"learn":[288.6331248],"iteration":744,"passed_time":0.6277880833,"remaining_time":0.2148804849},
{"learn":[288.5194364],"iteration":745,"passed_time":0.6285241928,"remaining_time":0.2140015348},
{"learn":[287.8960111],"iteration":746,"passed_time":0.6292605425,"remaining_time":0.2131230485},
{"learn":[287.4452039],"iteration":747,"passed_time":0.6300719428,"remaining_time":0.2122702267},
{"learn":[287.2704546],"iteration":748,"passed_time":0.6309279956,"remaining_time":0.2114324792},
{"learn":[287.0540846],"iteration":749,"passed_time":0.6317127724,"remaining_time":0.2105709241},
{"learn":[286.7844348],"iteration":750,"passed_time":0.6324833631,"remaining_time":0.2097048701},
{"learn":[286.5264595],"iteration":751,"passed_time":0.6332442122,"remaining_time":0.2088358572},
{"learn":[286.3335268],"iteration":752,"passed_time":0.63397053,"remaining_time":0.2079558047},
{"learn":[286.059881],"iteration":753,"passed_time":0.6346969379,"remaining_time":0.2070761893},
{"learn":[285.7660613],"iteration":754,"passed_time":0.6356768787,"remaining_time":0.206279252},
{"learn":[285.5805376],"iteration":755,"passed_time":0.6367095125,"remaining_time":0.2054988374},
{"learn":[285.5070486],"iteration":756,"passed_time":0.6376594875,"remaining_time":0.2046912225},
{"learn":[285.322196],"iteration":757,"passed_time":0.6384444145,"remaining_time":0.2038305387},
{"learn":[284.7157921],"iteration":758,"passed_time":0.639295171,"remaining_time":0.2029909568},
{"learn":[283.9656998],"iteration":759,"passed_time":0.6402833909,"remaining_time":0.202194755},
{"learn":[283.3730634],"iteration":760,"passed_time":0.6412753452,"remaining_time":0.2013992214},
{"learn":[283.1171798],"iteration":761,"passed_time":0.6421408193,"remaining_time":0.200563668},
{"learn":[282.630123],"iteration":762,"passed_time":0.6430642832,"remaining_time":0.1997460486},
{"learn":[282.5577853],"iteration":763,"passed_time":0.6438133982,"remaining_time":0.1988742958},
{"learn":[282.3356981],"iteration":764,"passed_time":0.6445694315,"remaining_time":0.1980049888},
{"learn":[282.1689601],"iteration":765,"passed_time":0.6454865372,"remaining_time":0.1971851824},
{"learn":[281.9865585],"iteration":766,"passed_time":0.6462548752,"remaining_time":0.1963199295},
{"learn":[281.7265877],"iteration":767,"passed_time":0.6470974419,"remaining_time":0.1954773523},
{"learn":[281.4714449],"iteration":768,"passed_time":0.6479556676,"remaining_time":0.1946394788},
{"learn":[281.1511101],"iteration":769,"passed_time":0.6487079564,"remaining_time":0.1937699091},
{"learn":[281.0781742],"iteration":770,"passed_time":0.6494747217,"remaining_time":0.1929049433},
{"learn":[280.6995465],"iteration":771,"passed_time":0.6502141952,"remaining_time":0.1920321717},
{"learn":[280.4862916],"iteration":772,"passed_time":0.6509510757,"remaining_time":0.1911589834},
{"learn":[280.0173118],"iteration":773,"passed_time":0.6516920309,"remaining_time":0.1902873372},
{"learn":[279.8075718],"iteration":774,"passed_time":0.6524272994,"remaining_time":0.1894143773},
{"learn":[279.3854515],"iteration":775,"passed_time":0.6532436548,"remaining_time":0.1885651787},
{"learn":[279.1865801],"iteration":776,"passed_time":0.6539941915,"remaining_time":0.1876971747},
{"learn":[279.0216984],"iteration":777,"passed_time":0.6547361881,"remaining_time":0.1868270357},
{"learn":[278.7419007],"iteration":778,"passed_time":0.6555267234,"remaining_time":0.185970996},
{"learn":[278.6074822],"iteration":779,"passed_time":0.6562724644,"remaining_time":0.18510249},
{"learn":[278.5498022],"iteration":780,"passed_time":0.656986898,"remaining_time":0.1842255194},
{"learn":[278.1443472],"iteration":781,"passed_time":0.6577419602,"remaining_time":0.1833602907},
{"learn":[277.5833125],"iteration":782,"passed_time":0.6584690088,"remaining_time":0.1824875797},
{"learn":[277.0348676],"iteration":783,"passed_time":0.6592321306,"remaining_time":0.1816251788},
{"learn":[276.9213733],"iteration":784,"passed_time":0.6599987666,"remaining_time":0.1807639934},
{"learn":[276.644848],"iteration":785,"passed_time":0.6608354763,"remaining_time":0.1799221271},
{"learn":[276.4995261],"iteration":786,"passed_time":0.661585162,"remaining_time":0.1790567211},
{"learn":[275.9616678],"iteration":787,"passed_time":0.6623397436,"remaining_time":0.1781929259},
{"learn":[275.5661345],"iteration":788,"passed_time":0.6630767341,"remaining_time":0.1773247033},
{"learn":[275.4386384],"iteration":789,"passed_time":0.6638351903,"remaining_time":0.1764625189},
{"learn":[275.314463],"iteration":790,"passed_time":0.6645747539,"remaining_time":0.175595605},
{"learn":[275.0508914],"iteration":791,"passed_time":0.6653558772,"remaining_time":0.1747399273},
{"learn":[274.8654324],"iteration":792,"passed_time":0.6661281899,"remaining_time":0.1738821379},
{"learn":[274.6994409],"iteration":793,"passed_time":0.666880629,"remaining_time":0.1730194075},
{"learn":[274.5316217],"iteration":794,"passed_time":0.6676343895,"remaining_time":0.1721572954},
{"learn":[274.2631578],"iteration":795,"passed_time":0.6683651126,"remaining_time":0.1712895515},
{"learn":[273.7434811],"iteration":796,"passed_time":0.6691159997,"remaining_time":0.1704272873},
{"learn":[273.5317382],"iteration":797,"passed_time":0.6698599786,"remaining_time":0.1695635535},
{"learn":[273.2973392],"iteration":798,"passed_time":0.6706539973,"remaining_time":0.1687127077},
{"learn":[273.1955147],"iteration":799,"passed_time":0.6713910379,"remaining_time":0.1678477595},
{"learn":[272.8514859],"iteration":800,"passed_time":0.672138471,"remaining_time":0.1669857125},
{"learn":[272.7529981],"iteration":801,"passed_time":0.6729031045,"remaining_time":0.1661281979},
{"learn":[272.6065319],"iteration":802,"passed_time":0.6736680185,"remaining_time":0.1652709834},
{"learn":[272.372953],"iteration":803,"passed_time":0.6745578018,"remaining_time":0.1644444393},
{"learn":[272.3155632],"iteration":804,"passed_time":0.6753329071,"remaining_time":0.1635899589},
{"learn":[272.1448163],"iteration":805,"passed_time":0.6760702681,"remaining_time":0.1627265906},
{"learn":[271.7702924],"iteration":806,"passed_time":0.676829305,"remaining_time":0.1618687185},
{"learn":[271.4992433],"iteration":807,"passed_time":0.67753655,"remaining_time":0.1609987842},
{"learn":[271.1496882],"iteration":808,"passed_time":0.6783181839,"remaining_time":0.1601468147},
{"learn":[271.0549428],"iteration":809,"passed_time":0.6791340395,"remaining_time":0.1593030463},
{"learn":[270.7851189],"iteration":810,"passed_time":0.6800001243,"remaining_time":0.1584710524},
{"learn":[270.5760884],"iteration":811,"passed_time":0.680780817,"remaining_time":0.1576192039},
{"learn":[270.4220296],"iteration":812,"passed_time":0.6815219926,"remaining_time":0.1567584411},
{"learn":[270.3249699],"iteration":813,"passed_time":0.6822267646,"remaining_time":0.1558896538},
{"learn":[270.2538825],"iteration":814,"passed_time":0.6829285631,"remaining_time":0.1550205941},
{"learn":[270.0275416],"iteration":815,"passed_time":0.6836675761,"remaining_time":0.1541603358},
{"learn":[269.6163121],"iteration":816,"passed_time":0.6844589616,"remaining_time":0.1533121052},
{"learn":[269.525072],"iteration":817,"passed_time":0.6851837977,"remaining_time":0.1524492068},
{"learn":[269.2972453],"iteration":818,"passed_time":0.6859439859,"remaining_time":0.1515944584},
{"learn":[269.1360991],"iteration":819,"passed_time":0.6866957741,"remaining_time":0.1507380968},
{"learn":[268.8530065],"iteration":820,"passed_time":0.6874382112,"remaining_time":0.149879951},
{"learn":[268.7848087],"iteration":821,"passed_time":0.6882343324,"remaining_time":0.1490337119},
{"learn":[268.4727473],"iteration":822,"passed_time":0.6889826765,"remaining_time":0.1481773193},
{"learn":[268.2420709],"iteration":823,"passed_time":0.6897307603,"remaining_time":0.1473211333},
{"learn":[268.1878253],"iteration":824,"passed_time":0.6904513813,"remaining_time":0.1464593839},
{"learn":[268.1279451],"iteration":825,"passed_time":0.6911798417,"remaining_time":0.1455996277},
{"learn":[267.7628814],"iteration":826,"passed_time":0.6919433439,"remaining_time":0.1447475193},
{"learn":[267.676621],"iteration":827,"passed_time":0.6926537126,"remaining_time":0.1438845876},
{"learn":[267.2782241],"iteration":828,"passed_time":0.6933904929,"remaining_time":0.143027472},
{"learn":[267.0448086],"iteration":829,"passed_time":0.6941185828,"remaining_time":0.1421688664},
{"learn":[266.8777712],"iteration":830,"passed_time":0.6948696102,"remaining_time":0.1413152396},
{"learn":[266.6576694],"iteration":831,"passed_time":0.695616883,"remaining_time":0.1404611014},
{"learn":[266.260517],"iteration":832,"passed_time":0.6963593801,"remaining_time":0.1396062623},
{"learn":[266.1696274],"iteration":833,"passed_time":0.6971040407,"remaining_time":0.1387521232},
{"learn":[265.9662619],"iteration":834,"passed_time":0.6978503223,"remaining_time":0.1378985667},
{"learn":[265.8225108],"iteration":835,"passed_time":0.6986206427,"remaining_time":0.1370499825},
{"learn":[265.4421342],"iteration":836,"passed_time":0.6993854365,"remaining_time":0.1362005091},
{"learn":[265.1874616],"iteration":837,"passed_time":0.7003516692,"remaining_time":0.1353901795},
{"learn":[264.9856274],"iteration":838,"passed_time":0.7015092526,"remaining_time":0.1346161975},
{"learn":[264.8112679],"iteration":839,"passed_time":0.7024049525,"remaining_time":0.1337914195},
{"learn":[264.2586328],"iteration":840,"passed_time":0.7034497602,"remaining_time":0.1329946634},
{"learn":[263.7769212],"iteration":841,"passed_time":0.70431951,"remaining_time":0.1321644686},
{"learn":[263.7050751],"iteration":842,"passed_time":0.7051181241,"remaining_time":0.1313209318},
{"learn":[263.3686146],"iteration":843,"passed_time":0.7060016092,"remaining_time":0.1304931884},
{"learn":[262.8970678],"iteration":844,"passed_time":0.7069359263,"remaining_time":0.1296746374},
{"learn":[262.6676632],"iteration":845,"passed_time":0.7078207426,"remaining_time":0.1288468019},
{"learn":[262.5051189],"iteration":846,"passed_time":0.7087388896,"remaining_time":0.1280248526},
{"learn":[262.3011046],"iteration":847,"passed_time":0.70982652,"remaining_time":0.1272330555},
{"learn":[262.0818333],"iteration":848,"passed_time":0.7109621259,"remaining_time":0.1264490942},
{"learn":[261.9729187],"iteration":849,"passed_time":0.7118487753,"remaining_time":0.1256203721},
{"learn":[261.7306125],"iteration":850,"passed_time":0.712743284,"remaining_time":0.1247928899},
{"learn":[261.5429463],"iteration":851,"passed_time":0.7135509599,"remaining_time":0.1239501667},
{"learn":[261.2113352],"iteration":852,"passed_time":0.7143921541,"remaining_time":0.1231133021},
{"learn":[260.9888023],"iteration":853,"passed_time":0.7152693121,"remaining_time":0.1222825756},
{"learn":[260.9094297],"iteration":854,"passed_time":0.716129771,"remaining_time":0.1214489085},
{"learn":[260.7724177],"iteration":855,"passed_time":0.7171382651,"remaining_time":0.120640082},
{"learn":[260.5583952],"iteration":856,"passed_time":0.717960097,"remaining_time":0.1197996428},
{"learn":[260.375037],"iteration":857,"passed_time":0.7189125255,"remaining_time":0.1189808609},
{"learn":[260.3229045],"iteration":858,"passed_time":0.7196632525,"remaining_time":0.1181286596},
{"learn":[260.0828767],"iteration":859,"passed_time":0.7204618266,"remaining_time":0.1172844834},
{"learn":[259.928197],"iteration":860,"passed_time":0.7213337684,"remaining_time":0.1164522576},
{"learn":[259.8528481],"iteration":861,"passed_time":0.7220874789,"remaining_time":0.1156010117},
{"learn":[259.3968219],"iteration":862,"passed_time":0.7228863935,"remaining_time":0.1147571679},
{"learn":[259.2490467],"iteration":863,"passed_time":0.7236368801,"remaining_time":0.1139058052},
{"learn":[259.0298986],"iteration":864,"passed_time":0.7245147994,"remaining_time":0.1130745641},
{"learn":[258.6638241],"iteration":865,"passed_time":0.7253917468,"remaining_time":0.1122430648},
{"learn":[258.5312926],"iteration":866,"passed_time":0.7263102042,"remaining_time":0.1114178283},
{"learn":[258.212477],"iteration":867,"passed_time":0.7270964436,"remaining_time":0.1105722702},
{"learn":[258.0167621],"iteration":868,"passed_time":0.727834125,"remaining_time":0.1097195286},
{"learn":[257.6629205],"iteration":869,"passed_time":0.7285872047,"remaining_time":0.1088693524},
{"learn":[257.5893111],"iteration":870,"passed_time":0.7293203907,"remaining_time":0.1080164528},
{"learn":[257.3915686],"iteration":871,"passed_time":0.7301369158,"remaining_time":0.107176061},
{"learn":[257.1706886],"iteration":872,"passed_time":0.731007957,"remaining_time":0.1063436547},
{"learn":[256.5084026],"iteration":873,"passed_time":0.7318505437,"remaining_time":0.1055070578},
{"learn":[256.3684608],"iteration":874,"passed_time":0.7327066969,"remaining_time":0.1046723853},
{"learn":[256.1406509],"iteration":875,"passed_time":0.7334530086,"remaining_time":0.1038221154},
{"learn":[255.9315589],"iteration":876,"passed_time":0.7342105838,"remaining_time":0.1029736623},
{"learn":[255.6383],"iteration":877,"passed_time":0.734969891,"remaining_time":0.1021256568},
{"learn":[255.3630919],"iteration":878,"passed_time":0.7357252034,"remaining_time":0.1012773033},
{"learn":[254.7144679],"iteration":879,"passed_time":0.7364783032,"remaining_time":0.1004288595},
{"learn":[254.5560531],"iteration":880,"passed_time":0.7373645521,"remaining_time":0.09959861714},
{"learn":[254.3664148],"iteration":881,"passed_time":0.7382277031,"remaining_time":0.09876515756},
{"learn":[254.1869568],"iteration":882,"passed_time":0.7391111681,"remaining_time":0.09793432239},
{"learn":[253.8915148],"iteration":883,"passed_time":0.7398463064,"remaining_time":0.09708390446},
{"learn":[253.2565593],"iteration":884,"passed_time":0.7406723434,"remaining_time":0.09624555874},
{"learn":[253.0471595],"iteration":885,"passed_time":0.7414599244,"remaining_time":0.09540229275},
{"learn":[252.9776226],"iteration":886,"passed_time":0.7421868429,"remaining_time":0.09455142418},
{"learn":[252.7043269],"iteration":887,"passed_time":0.7429489134,"remaining_time":0.09370526836},
{"learn":[252.5090444],"iteration":888,"passed_time":0.7438449245,"remaining_time":0.09287602544},
{"learn":[252.372754],"iteration":889,"passed_time":0.7449291299,"remaining_time":0.09206989246},
{"learn":[252.2433132],"iteration":890,"passed_time":0.7457735583,"remaining_time":0.0912338023},
{"learn":[251.5382998],"iteration":891,"passed_time":0.7467210094,"remaining_time":0.09041016706},
{"learn":[251.381047],"iteration":892,"passed_time":0.7477642968,"remaining_time":0.08959773769},
{"learn":[250.6963329],"iteration":893,"passed_time":0.7485762352,"remaining_time":0.08875736122},
{"learn":[250.5235325],"iteration":894,"passed_time":0.7494239889,"remaining_time":0.0879212501},
{"learn":[250.2490998],"iteration":895,"passed_time":0.750374694,"remaining_time":0.08709706269},
{"learn":[249.9348798],"iteration":896,"passed_time":0.7514478662,"remaining_time":0.08628665576},
{"learn":[249.8570264],"iteration":897,"passed_time":0.7523049502,"remaining_time":0.08545111907},
{"learn":[249.4287684],"iteration":898,"passed_time":0.7530670107,"remaining_time":0.08460485882},
{"learn":[249.2764832],"iteration":899,"passed_time":0.7538199612,"remaining_time":0.08375777346},
{"learn":[248.8571377],"iteration":900,"passed_time":0.7545754138,"remaining_time":0.08291117199},
{"learn":[248.6661279],"iteration":901,"passed_time":0.7553190623,"remaining_time":0.08206349014},
{"learn":[248.5326057],"iteration":902,"passed_time":0.7562108978,"remaining_time":0.08123195691},
{"learn":[248.1218853],"iteration":903,"passed_time":0.7572058274,"remaining_time":0.08041123831},
{"learn":[248.0437851],"iteration":904,"passed_time":0.7579350587,"remaining_time":0.07956224373},
{"learn":[247.8323242],"iteration":905,"passed_time":0.758820656,"remaining_time":0.07872973693},
{"learn":[247.6663182],"iteration":906,"passed_time":0.7596808045,"remaining_time":0.07789450366},
{"learn":[247.5391806],"iteration":907,"passed_time":0.7604224806,"remaining_time":0.07704721169},
{"learn":[247.237825],"iteration":908,"passed_time":0.7613887042,"remaining_time":0.07622263156},
{"learn":[246.6469831],"iteration":909,"passed_time":0.7621721903,"remaining_time":0.07537966718},
{"learn":[246.5801032],"iteration":910,"passed_time":0.7630079094,"remaining_time":0.07454193626},
{"learn":[246.0925385],"iteration":911,"passed_time":0.7639239033,"remaining_time":0.07371195558},
{"learn":[245.8954572],"iteration":912,"passed_time":0.7649777841,"remaining_time":0.07289492576},
{"learn":[245.7223326],"iteration":913,"passed_time":0.7657306035,"remaining_time":0.07204905022},
{"learn":[245.5126434],"iteration":914,"passed_time":0.7664897606,"remaining_time":0.07120396683},
{"learn":[245.2642559],"iteration":915,"passed_time":0.7672420294,"remaining_time":0.07035843938},
{"learn":[245.0907564],"iteration":916,"passed_time":0.7680796201,"remaining_time":0.06952083803},
{"learn":[244.7635212],"iteration":917,"passed_time":0.7688345221,"remaining_time":0.06867585056},
{"learn":[244.6046178],"iteration":918,"passed_time":0.7699359072,"remaining_time":0.06786159791},
{"learn":[244.3080385],"iteration":919,"passed_time":0.7707435621,"remaining_time":0.06702117932},
{"learn":[243.91631],"iteration":920,"passed_time":0.7715324347,"remaining_time":0.06617922078},
{"learn":[243.8502748],"iteration":921,"passed_time":0.7722716879,"remaining_time":0.06533317967},
{"learn":[243.6959953],"iteration":922,"passed_time":0.7730789725,"remaining_time":0.06449304537},
{"learn":[243.444568],"iteration":923,"passed_time":0.7739280269,"remaining_time":0.0636564178},
{"learn":[243.3952595],"iteration":924,"passed_time":0.7746577488,"remaining_time":0.06281008774},
{"learn":[243.1626211],"iteration":925,"passed_time":0.7754012771,"remaining_time":0.06196511286},
{"learn":[242.9632222],"iteration":926,"passed_time":0.7763706562,"remaining_time":0.06113814229},
{"learn":[242.7420844],"iteration":927,"passed_time":0.7774547106,"remaining_time":0.06031976203},
{"learn":[242.5621843],"iteration":928,"passed_time":0.7786155183,"remaining_time":0.05950667578},
{"learn":[242.4130949],"iteration":929,"passed_time":0.7793689785,"remaining_time":0.05866218118},
{"learn":[242.1372354],"iteration":930,"passed_time":0.7800974389,"remaining_time":0.05781602931},
{"learn":[241.9010852],"iteration":931,"passed_time":0.7808351903,"remaining_time":0.05697080788},
{"learn":[241.7476704],"iteration":932,"passed_time":0.7815669146,"remaining_time":0.05612538401},
{"learn":[241.5224467],"iteration":933,"passed_time":0.7826115416,"remaining_time":0.0553023145},
{"learn":[241.4751095],"iteration":934,"passed_time":0.7834639295,"remaining_time":0.05446540686},
{"learn":[241.3142192],"iteration":935,"passed_time":0.7842309159,"remaining_time":0.05362262673},
{"learn":[240.7422872],"iteration":936,"passed_time":0.7850059619,"remaining_time":0.05278055026},
{"learn":[240.567149],"iteration":937,"passed_time":0.7857566288,"remaining_time":0.05193700531},
{"learn":[240.4644917],"iteration":938,"passed_time":0.7865028704,"remaining_time":0.05109337071},
{"learn":[240.2006292],"iteration":939,"passed_time":0.7873745719,"remaining_time":0.0502579514},
{"learn":[240.1579679],"iteration":940,"passed_time":0.7881096001,"remaining_time":0.04941388566},
{"learn":[239.9025576],"iteration":941,"passed_time":0.789153388,"remaining_time":0.04858906211},
{"learn":[239.7686299],"iteration":942,"passed_time":0.790297344,"remaining_time":0.04776982885},
{"learn":[239.5230639],"iteration":943,"passed_time":0.7911117578,"remaining_time":0.04693035852},
{"learn":[239.2853052],"iteration":944,"passed_time":0.791907139,"remaining_time":0.04608983349},
{"learn":[239.0550504],"iteration":945,"passed_time":0.7928179556,"remaining_time":0.04525599323},
{"learn":[238.9530757],"iteration":946,"passed_time":0.7936312081,"remaining_time":0.04441653012},
{"learn":[238.2949912],"iteration":947,"passed_time":0.7944884915,"remaining_time":0.04357953751},
{"learn":[238.0737284],"iteration":948,"passed_time":0.7953567097,"remaining_time":0.04274308977},
{"learn":[237.9760671],"iteration":949,"passed_time":0.7963528607,"remaining_time":0.04191330846},
{"learn":[237.8172858],"iteration":950,"passed_time":0.7973275352,"remaining_time":0.04108207069},
{"learn":[237.3193543],"iteration":951,"passed_time":0.7981130738,"remaining_time":0.04024099532},
{"learn":[237.1781091],"iteration":952,"passed_time":0.798925794,"remaining_time":0.03940137704},
{"learn":[237.0042227],"iteration":953,"passed_time":0.7997411582,"remaining_time":0.03856194264},
{"learn":[236.8060426],"iteration":954,"passed_time":0.8005280683,"remaining_time":0.03772121788},
{"learn":[236.7122574],"iteration":955,"passed_time":0.8012893279,"remaining_time":0.03687942513},
{"learn":[236.622348],"iteration":956,"passed_time":0.8023353085,"remaining_time":0.0360505938},
{"learn":[236.4290546],"iteration":957,"passed_time":0.8032033456,"remaining_time":0.03521350784},
{"learn":[236.042597],"iteration":958,"passed_time":0.8040642133,"remaining_time":0.03437605083},
{"learn":[235.9554518],"iteration":959,"passed_time":0.804948801,"remaining_time":0.03353953338},
{"learn":[235.7869984],"iteration":960,"passed_time":0.8057585777,"remaining_time":0.03269987984},
{"learn":[235.1556481],"iteration":961,"passed_time":0.8065080331,"remaining_time":0.03185790568},
{"learn":[235.0997102],"iteration":962,"passed_time":0.8072550156,"remaining_time":0.03101602864},
{"learn":[235.0192784],"iteration":963,"passed_time":0.8080007975,"remaining_time":0.03017430364},
{"learn":[234.4767183],"iteration":964,"passed_time":0.8088605539,"remaining_time":0.02933691128},
{"learn":[234.0961803],"iteration":965,"passed_time":0.8096316052,"remaining_time":0.02849635049},
{"learn":[233.7239197],"iteration":966,"passed_time":0.810496098,"remaining_time":0.02765912227},
{"learn":[233.3596966],"iteration":967,"passed_time":0.8112609018,"remaining_time":0.02681854221},
{"learn":[233.0984886],"iteration":968,"passed_time":0.8120869388,"remaining_time":0.0259800775},
{"learn":[232.7459793],"iteration":969,"passed_time":0.8128604129,"remaining_time":0.02514001277},
{"learn":[232.4010012],"iteration":970,"passed_time":0.8136936885,"remaining_time":0.02430187123},
{"learn":[232.346298],"iteration":971,"passed_time":0.8145663016,"remaining_time":0.02346487289},
{"learn":[232.0085083],"iteration":972,"passed_time":0.8155606892,"remaining_time":0.02263118048},
{"learn":[231.8321631],"iteration":973,"passed_time":0.8163261938,"remaining_time":0.02179104829},
{"learn":[231.5035359],"iteration":974,"passed_time":0.8170884445,"remaining_time":0.02095098576},
{"learn":[231.4509679],"iteration":975,"passed_time":0.8178795205,"remaining_time":0.02011179149},
{"learn":[231.1766546],"iteration":976,"passed_time":0.8188036038,"remaining_time":0.01927582691},
{"learn":[231.0610863],"iteration":977,"passed_time":0.8195811528,"remaining_time":0.01843638585},
{"learn":[230.9100767],"iteration":978,"passed_time":0.820317002,"remaining_time":0.01759617675},
{"learn":[230.8331736],"iteration":979,"passed_time":0.8211387043,"remaining_time":0.01675793274},
{"learn":[230.6357698],"iteration":980,"passed_time":0.8220226407,"remaining_time":0.0159209278},
{"learn":[230.5152829],"iteration":981,"passed_time":0.8228782721,"remaining_time":0.01508330845},
{"learn":[229.9886338],"iteration":982,"passed_time":0.823684665,"remaining_time":0.01424480092},
{"learn":[229.9384547],"iteration":983,"passed_time":0.8244418197,"remaining_time":0.01340555804},
{"learn":[229.6180745],"iteration":984,"passed_time":0.825189533,"remaining_time":0.01256633807},
{"learn":[229.5067033],"iteration":985,"passed_time":0.8259356044,"remaining_time":0.01172728039},
{"learn":[229.2195824],"iteration":986,"passed_time":0.8267153661,"remaining_time":0.01088885487},
{"learn":[229.1781871],"iteration":987,"passed_time":0.8275161629,"remaining_time":0.0100508036},
{"learn":[229.034446],"iteration":988,"passed_time":0.8284987076,"remaining_time":0.009214849124},
{"learn":[228.9271806],"iteration":989,"passed_time":0.8293566819,"remaining_time":0.008377340221},
{"learn":[228.4093207],"iteration":990,"passed_time":0.8300907189,"remaining_time":0.00753866445},
{"learn":[228.3620236],"iteration":991,"passed_time":0.8308135125,"remaining_time":0.006700108972},
{"learn":[228.096339],"iteration":992,"passed_time":0.8315637889,"remaining_time":0.005861980385},
{"learn":[227.5909211],"iteration":993,"passed_time":0.8323176797,"remaining_time":0.00502405038},
{"learn":[227.2516364],"iteration":994,"passed_time":0.8332025277,"remaining_time":0.004186947375},
{"learn":[227.2214782],"iteration":995,"passed_time":0.8340726173,"remaining_time":0.003349689226},
{"learn":[227.1029904],"iteration":996,"passed_time":0.8349007668,"remaining_time":0.002512239017},
{"learn":[226.9751438],"iteration":997,"passed_time":0.8356707676,"remaining_time":0.001674690917},
{"learn":[226.8728244],"iteration":998,"passed_time":0.8367804117,"remaining_time":0.0008376180297},
{"learn":[226.8334626],"iteration":999,"passed_time":0.8376029536,"remaining_time":0}
]}